{
  "venues": [
    {
      "id": "568WWV4J",
      "riskyWindow": {
        "from": "2021-07-24T00:00:00Z",
        "until": "2021-07-24T22:59:00Z"
      },
      "messageType": "M2"
    },
    {
      "id": "R9J9Y325",
      "riskyWindow": {
        "from": "2021-07-25T00:00:00Z",
        "until": "2021-07-25T22:59:00Z"
      },
      "messageType": "M2"
    },
    {
      "id": "54983WYR",
      "riskyWindow": {
        "from": "2021-07-27T00:00:00Z",
        "until": "2021-07-27T22:59:00Z"
      },
      "messageType": "M2"
    },
    {
      "id": "RP9VKY2J",
      "riskyWindow": {
        "from": "2021-07-24T00:00:00Z",
        "until": "2021-07-24T22:59:00Z"
      },
      "messageType": "M2"
    },
    {
      "id": "5YM8W3M5",
      "riskyWindow": {
        "from": "2021-07-26T00:00:00Z",
        "until": "2021-07-26T22:59:00Z"
      },
      "messageType": "M2"
    },
    {
      "id": "5V2WXXP5",
      "riskyWindow": {
        "from": "2021-07-24T00:00:00Z",
        "until": "2021-07-24T22:59:00Z"
      },
      "messageType": "M2"
    },
    {
      "id": "53362XW5",
      "riskyWindow": {
        "from": "2021-07-25T00:00:00Z",
        "until": "2021-07-25T22:59:00Z"
      },
      "messageType": "M2"
    },
    {
      "id": "5X2PY6Y5",
      "riskyWindow": {
        "from": "2021-07-25T00:00:00Z",
        "until": "2021-07-25T22:59:00Z"
      },
      "messageType": "M2"
    },
    {
      "id": "5V894YK5",
      "riskyWindow": {
        "from": "2021-07-25T00:00:00Z",
        "until": "2021-07-25T22:59:00Z"
      },
      "messageType": "M2"
    },
    {
      "id": "RK63PMK5",
      "riskyWindow": {
        "from": "2021-07-24T00:00:00Z",
        "until": "2021-07-24T22:59:00Z"
      },
      "messageType": "M2"
    },
    {
      "id": "54K222VR",
      "riskyWindow": {
        "from": "2021-07-26T00:00:00Z",
        "until": "2021-07-26T22:59:00Z"
      },
      "messageType": "M2"
    },
    {
      "id": "V5M98295",
      "riskyWindow": {
        "from": "2021-07-26T00:00:00Z",
        "until": "2021-07-26T22:59:00Z"
      },
      "messageType": "M2"
    },
    {
      "id": "5V6J9M45",
      "riskyWindow": {
        "from": "2021-07-25T00:00:00Z",
        "until": "2021-07-25T22:59:00Z"
      },
      "messageType": "M2"
    },
    {
      "id": "53K3XJ65",
      "riskyWindow": {
        "from": "2021-07-25T00:00:00Z",
        "until": "2021-07-25T22:59:00Z"
      },
      "messageType": "M2"
    },
    {
      "id": "RJ8VVVVR",
      "riskyWindow": {
        "from": "2021-07-25T00:00:00Z",
        "until": "2021-07-25T22:59:00Z"
      },
      "messageType": "M2"
    },
    {
      "id": "4RK2X325",
      "riskyWindow": {
        "from": "2021-07-24T00:00:00Z",
        "until": "2021-07-24T22:59:00Z"
      },
      "messageType": "M2"
    },
    {
      "id": "R82V4YVR",
      "riskyWindow": {
        "from": "2021-07-24T00:00:00Z",
        "until": "2021-07-24T22:59:00Z"
      },
      "messageType": "M2"
    },
    {
      "id": "R86VK22R",
      "riskyWindow": {
        "from": "2021-07-25T00:00:00Z",
        "until": "2021-07-25T22:59:00Z"
      },
      "messageType": "M2"
    },
    {
      "id": "53W3XV4Y",
      "riskyWindow": {
        "from": "2021-07-25T00:00:00Z",
        "until": "2021-07-25T22:59:00Z"
      },
      "messageType": "M2"
    },
    {
      "id": "566Y4K95",
      "riskyWindow": {
        "from": "2021-07-25T00:00:00Z",
        "until": "2021-07-25T22:59:00Z"
      },
      "messageType": "M2"
    },
    {
      "id": "5WV6KMPJ",
      "riskyWindow": {
        "from": "2021-07-24T00:00:00Z",
        "until": "2021-07-24T22:59:00Z"
      },
      "messageType": "M2"
    },
    {
      "id": "53WMK2XW",
      "riskyWindow": {
        "from": "2021-07-25T23:00:00Z",
        "until": "2021-07-26T22:59:59Z"
      },
      "messageType": "M2"
    },
    {
      "id": "562WP995",
      "riskyWindow": {
        "from": "2021-07-24T00:00:00Z",
        "until": "2021-07-24T22:59:00Z"
      },
      "messageType": "M2"
    },
    {
      "id": "5WV6KM3M",
      "riskyWindow": {
        "from": "2021-07-24T00:00:00Z",
        "until": "2021-07-24T22:59:00Z"
      },
      "messageType": "M2"
    },
    {
      "id": "KRP4VWXR",
      "riskyWindow": {
        "from": "2021-07-24T00:00:00Z",
        "until": "2021-07-24T22:59:00Z"
      },
      "messageType": "M2"
    },
    {
      "id": "542MW9WP",
      "riskyWindow": {
        "from": "2021-07-24T00:00:00Z",
        "until": "2021-07-24T22:59:00Z"
      },
      "messageType": "M2"
    },
    {
      "id": "X5XPY9W5",
      "riskyWindow": {
        "from": "2021-07-24T00:00:00Z",
        "until": "2021-07-24T22:59:00Z"
      },
      "messageType": "M2"
    },
    {
      "id": "R9JWK6V5",
      "riskyWindow": {
        "from": "2021-07-24T00:00:00Z",
        "until": "2021-07-24T22:59:00Z"
      },
      "messageType": "M2"
    },
    {
      "id": "R99346XR",
      "riskyWindow": {
        "from": "2021-07-25T00:00:00Z",
        "until": "2021-07-25T22:59:00Z"
      },
      "messageType": "M2"
    },
    {
      "id": "52PWVW85",
      "riskyWindow": {
        "from": "2021-07-24T00:00:00Z",
        "until": "2021-07-24T22:59:00Z"
      },
      "messageType": "M2"
    },
    {
      "id": "52WWV98R",
      "riskyWindow": {
        "from": "2021-07-26T23:00:00Z",
        "until": "2021-07-27T22:59:59Z"
      },
      "messageType": "M2"
    },
    {
      "id": "5VX44823",
      "riskyWindow": {
        "from": "2021-07-26T00:00:00Z",
        "until": "2021-07-26T22:59:00Z"
      },
      "messageType": "M2"
    },
    {
      "id": "RKJJ6MK5",
      "riskyWindow": {
        "from": "2021-07-27T00:00:00Z",
        "until": "2021-07-27T22:59:00Z"
      },
      "messageType": "M2"
    },
    {
      "id": "5WVPJYWR",
      "riskyWindow": {
        "from": "2021-07-24T00:00:00Z",
        "until": "2021-07-24T22:59:00Z"
      },
      "messageType": "M2"
    },
    {
      "id": "5VPK2PP5",
      "riskyWindow": {
        "from": "2021-07-24T00:00:00Z",
        "until": "2021-07-24T22:59:00Z"
      },
      "messageType": "M2"
    },
    {
      "id": "53MVMK25",
      "riskyWindow": {
        "from": "2021-07-24T00:00:00Z",
        "until": "2021-07-24T22:59:00Z"
      },
      "messageType": "M2"
    },
    {
      "id": "5X2XP868",
      "riskyWindow": {
        "from": "2021-07-24T00:00:00Z",
        "until": "2021-07-24T22:59:00Z"
      },
      "messageType": "M2"
    },
    {
      "id": "RKKP446R",
      "riskyWindow": {
        "from": "2021-07-24T00:00:00Z",
        "until": "2021-07-24T22:59:00Z"
      },
      "messageType": "M2"
    },
    {
      "id": "5X2YPVVK",
      "riskyWindow": {
        "from": "2021-07-25T00:00:00Z",
        "until": "2021-07-25T22:59:00Z"
      },
      "messageType": "M2"
    },
    {
      "id": "RJ2Y3Y9R",
      "riskyWindow": {
        "from": "2021-07-25T00:00:00Z",
        "until": "2021-07-25T22:59:00Z"
      },
      "messageType": "M2"
    },
    {
      "id": "RKY2P62R",
      "riskyWindow": {
        "from": "2021-07-26T00:00:00Z",
        "until": "2021-07-26T22:59:00Z"
      },
      "messageType": "M2"
    },
    {
      "id": "52K38J4R",
      "riskyWindow": {
        "from": "2021-07-25T23:00:00Z",
        "until": "2021-07-26T22:59:59Z"
      },
      "messageType": "M2"
    },
    {
      "id": "RJV2WXVW",
      "riskyWindow": {
        "from": "2021-07-26T00:00:00Z",
        "until": "2021-07-26T22:59:00Z"
      },
      "messageType": "M2"
    },
    {
      "id": "5VMXV34R",
      "riskyWindow": {
        "from": "2021-07-24T00:00:00Z",
        "until": "2021-07-24T22:59:00Z"
      },
      "messageType": "M2"
    },
    {
      "id": "RPV2XY2R",
      "riskyWindow": {
        "from": "2021-07-24T00:00:00Z",
        "until": "2021-07-24T22:59:00Z"
      },
      "messageType": "M2"
    },
    {
      "id": "5VX8PXV8",
      "riskyWindow": {
        "from": "2021-07-26T00:00:00Z",
        "until": "2021-07-26T22:59:00Z"
      },
      "messageType": "M2"
    },
    {
      "id": "532VJVVR",
      "riskyWindow": {
        "from": "2021-07-25T00:00:00Z",
        "until": "2021-07-25T22:59:00Z"
      },
      "messageType": "M2"
    },
    {
      "id": "53WPW445",
      "riskyWindow": {
        "from": "2021-07-24T00:00:00Z",
        "until": "2021-07-24T22:59:00Z"
      },
      "messageType": "M2"
    },
    {
      "id": "5WVJ3M9M",
      "riskyWindow": {
        "from": "2021-07-25T00:00:00Z",
        "until": "2021-07-25T22:59:00Z"
      },
      "messageType": "M2"
    },
    {
      "id": "5W8W4KXR",
      "riskyWindow": {
        "from": "2021-07-25T00:00:00Z",
        "until": "2021-07-25T22:59:00Z"
      },
      "messageType": "M2"
    },
    {
      "id": "R9J6XX3Y",
      "riskyWindow": {
        "from": "2021-07-25T00:00:00Z",
        "until": "2021-07-25T22:59:00Z"
      },
      "messageType": "M2"
    },
    {
      "id": "5M3KVY85",
      "riskyWindow": {
        "from": "2021-07-24T00:00:00Z",
        "until": "2021-07-24T22:59:00Z"
      },
      "messageType": "M2"
    },
    {
      "id": "5MWX982W",
      "riskyWindow": {
        "from": "2021-07-27T00:00:00Z",
        "until": "2021-07-27T22:59:00Z"
      },
      "messageType": "M2"
    },
    {
      "id": "5MWM9KVW",
      "riskyWindow": {
        "from": "2021-07-25T23:00:00Z",
        "until": "2021-07-26T22:59:59Z"
      },
      "messageType": "M2"
    },
    {
      "id": "RP9XY3VJ",
      "riskyWindow": {
        "from": "2021-07-25T00:00:00Z",
        "until": "2021-07-25T22:59:00Z"
      },
      "messageType": "M2"
    },
    {
      "id": "533KP6W5",
      "riskyWindow": {
        "from": "2021-07-25T00:00:00Z",
        "until": "2021-07-25T22:59:00Z"
      },
      "messageType": "M2"
    },
    {
      "id": "RKY32468",
      "riskyWindow": {
        "from": "2021-07-25T00:00:00Z",
        "until": "2021-07-25T22:59:00Z"
      },
      "messageType": "M2"
    },
    {
      "id": "5VW33VPR",
      "riskyWindow": {
        "from": "2021-07-26T00:00:00Z",
        "until": "2021-07-26T22:59:00Z"
      },
      "messageType": "M2"
    },
    {
      "id": "526V8X45",
      "riskyWindow": {
        "from": "2021-07-26T00:00:00Z",
        "until": "2021-07-26T22:59:00Z"
      },
      "messageType": "M2"
    },
    {
      "id": "5W3X9PM5",
      "riskyWindow": {
        "from": "2021-07-26T00:00:00Z",
        "until": "2021-07-26T22:59:00Z"
      },
      "messageType": "M2"
    },
    {
      "id": "5Y9V42P5",
      "riskyWindow": {
        "from": "2021-07-25T00:00:00Z",
        "until": "2021-07-25T22:59:00Z"
      },
      "messageType": "M2"
    },
    {
      "id": "544JMPM5",
      "riskyWindow": {
        "from": "2021-07-26T23:00:00Z",
        "until": "2021-07-27T22:59:59Z"
      },
      "messageType": "M2"
    },
    {
      "id": "R9J4XVV5",
      "riskyWindow": {
        "from": "2021-07-24T00:00:00Z",
        "until": "2021-07-24T22:59:00Z"
      },
      "messageType": "M2"
    },
    {
      "id": "R9Y3PPYR",
      "riskyWindow": {
        "from": "2021-07-24T00:00:00Z",
        "until": "2021-07-24T22:59:00Z"
      },
      "messageType": "M2"
    },
    {
      "id": "RJVPX9M8",
      "riskyWindow": {
        "from": "2021-07-24T00:00:00Z",
        "until": "2021-07-24T22:59:00Z"
      },
      "messageType": "M2"
    },
    {
      "id": "R8VJJX2K",
      "riskyWindow": {
        "from": "2021-07-24T00:00:00Z",
        "until": "2021-07-24T22:59:00Z"
      },
      "messageType": "M2"
    },
    {
      "id": "R86W699R",
      "riskyWindow": {
        "from": "2021-07-27T00:00:00Z",
        "until": "2021-07-27T22:59:00Z"
      },
      "messageType": "M2"
    },
    {
      "id": "RP8489VR",
      "riskyWindow": {
        "from": "2021-07-25T00:00:00Z",
        "until": "2021-07-25T22:59:00Z"
      },
      "messageType": "M2"
    },
    {
      "id": "5X2XP4J5",
      "riskyWindow": {
        "from": "2021-07-24T00:00:00Z",
        "until": "2021-07-24T22:59:00Z"
      },
      "messageType": "M2"
    },
    {
      "id": "RP89J42R",
      "riskyWindow": {
        "from": "2021-07-24T00:00:00Z",
        "until": "2021-07-24T22:59:00Z"
      },
      "messageType": "M2"
    },
    {
      "id": "5VX4XJXP",
      "riskyWindow": {
        "from": "2021-07-25T00:00:00Z",
        "until": "2021-07-25T22:59:00Z"
      },
      "messageType": "M2"
    },
    {
      "id": "5Y9Y83MW",
      "riskyWindow": {
        "from": "2021-07-26T23:00:00Z",
        "until": "2021-07-27T22:59:59Z"
      },
      "messageType": "M2"
    },
    {
      "id": "5WVVYY9X",
      "riskyWindow": {
        "from": "2021-07-25T00:00:00Z",
        "until": "2021-07-25T22:59:00Z"
      },
      "messageType": "M2"
    },
    {
      "id": "5MWW2MWW",
      "riskyWindow": {
        "from": "2021-07-25T00:00:00Z",
        "until": "2021-07-25T22:59:00Z"
      },
      "messageType": "M2"
    },
    {
      "id": "RP232W2R",
      "riskyWindow": {
        "from": "2021-07-25T00:00:00Z",
        "until": "2021-07-25T22:59:00Z"
      },
      "messageType": "M2"
    },
    {
      "id": "RJVMVY89",
      "riskyWindow": {
        "from": "2021-07-24T00:00:00Z",
        "until": "2021-07-24T22:59:00Z"
      },
      "messageType": "M2"
    },
    {
      "id": "5Y9VV9PX",
      "riskyWindow": {
        "from": "2021-07-25T00:00:00Z",
        "until": "2021-07-25T22:59:00Z"
      },
      "messageType": "M2"
    },
    {
      "id": "R98WPXP5",
      "riskyWindow": {
        "from": "2021-07-25T00:00:00Z",
        "until": "2021-07-25T22:59:00Z"
      },
      "messageType": "M2"
    },
    {
      "id": "5Y888Y8R",
      "riskyWindow": {
        "from": "2021-07-26T00:00:00Z",
        "until": "2021-07-26T22:59:00Z"
      },
      "messageType": "M2"
    },
    {
      "id": "548WWMY5",
      "riskyWindow": {
        "from": "2021-07-25T00:00:00Z",
        "until": "2021-07-25T22:59:00Z"
      },
      "messageType": "M2"
    },
    {
      "id": "R9PYVY25",
      "riskyWindow": {
        "from": "2021-07-25T00:00:00Z",
        "until": "2021-07-25T22:59:00Z"
      },
      "messageType": "M2"
    },
    {
      "id": "528X3WK5",
      "riskyWindow": {
        "from": "2021-07-25T23:00:00Z",
        "until": "2021-07-26T22:59:59Z"
      },
      "messageType": "M2"
    },
    {
      "id": "R8YV4P65",
      "riskyWindow": {
        "from": "2021-07-26T00:00:00Z",
        "until": "2021-07-26T22:59:00Z"
      },
      "messageType": "M2"
    },
    {
      "id": "5XVK2JY5",
      "riskyWindow": {
        "from": "2021-07-24T00:00:00Z",
        "until": "2021-07-24T22:59:00Z"
      },
      "messageType": "M2"
    },
    {
      "id": "5Y99PMW5",
      "riskyWindow": {
        "from": "2021-07-26T23:00:00Z",
        "until": "2021-07-27T22:59:59Z"
      },
      "messageType": "M2"
    },
    {
      "id": "J5W4K2VR",
      "riskyWindow": {
        "from": "2021-07-24T00:00:00Z",
        "until": "2021-07-24T22:59:00Z"
      },
      "messageType": "M2"
    },
    {
      "id": "R8VM32KM",
      "riskyWindow": {
        "from": "2021-07-24T00:00:00Z",
        "until": "2021-07-24T22:59:00Z"
      },
      "messageType": "M2"
    },
    {
      "id": "5WYMPPM5",
      "riskyWindow": {
        "from": "2021-07-27T00:00:00Z",
        "until": "2021-07-27T22:59:00Z"
      },
      "messageType": "M2"
    },
    {
      "id": "5M44YW9R",
      "riskyWindow": {
        "from": "2021-07-25T00:00:00Z",
        "until": "2021-07-25T22:59:00Z"
      },
      "messageType": "M2"
    },
    {
      "id": "RKYXYWX8",
      "riskyWindow": {
        "from": "2021-07-24T00:00:00Z",
        "until": "2021-07-24T22:59:00Z"
      },
      "messageType": "M2"
    },
    {
      "id": "RKVMKY65",
      "riskyWindow": {
        "from": "2021-07-27T00:00:00Z",
        "until": "2021-07-27T22:59:00Z"
      },
      "messageType": "M2"
    },
    {
      "id": "542YW6VP",
      "riskyWindow": {
        "from": "2021-07-25T00:00:00Z",
        "until": "2021-07-25T22:59:00Z"
      },
      "messageType": "M2"
    },
    {
      "id": "5VPVJW85",
      "riskyWindow": {
        "from": "2021-07-25T00:00:00Z",
        "until": "2021-07-25T22:59:00Z"
      },
      "messageType": "M2"
    },
    {
      "id": "R8V34W8R",
      "riskyWindow": {
        "from": "2021-07-24T00:00:00Z",
        "until": "2021-07-24T22:59:00Z"
      },
      "messageType": "M2"
    },
    {
      "id": "5Y4MW4XR",
      "riskyWindow": {
        "from": "2021-07-24T00:00:00Z",
        "until": "2021-07-24T22:59:00Z"
      },
      "messageType": "M2"
    },
    {
      "id": "5Y6J6WPR",
      "riskyWindow": {
        "from": "2021-07-24T00:00:00Z",
        "until": "2021-07-24T22:59:00Z"
      },
      "messageType": "M2"
    },
    {
      "id": "5MWYW2Y5",
      "riskyWindow": {
        "from": "2021-07-24T00:00:00Z",
        "until": "2021-07-24T22:59:00Z"
      },
      "messageType": "M2"
    },
    {
      "id": "5MWYXY85",
      "riskyWindow": {
        "from": "2021-07-25T00:00:00Z",
        "until": "2021-07-25T22:59:00Z"
      },
      "messageType": "M2"
    },
    {
      "id": "5WVY66WX",
      "riskyWindow": {
        "from": "2021-07-24T00:00:00Z",
        "until": "2021-07-24T22:59:00Z"
      },
      "messageType": "M2"
    },
    {
      "id": "RKYX43JK",
      "riskyWindow": {
        "from": "2021-07-26T00:00:00Z",
        "until": "2021-07-26T22:59:00Z"
      },
      "messageType": "M2"
    },
    {
      "id": "4RJ83VVR",
      "riskyWindow": {
        "from": "2021-07-24T00:00:00Z",
        "until": "2021-07-24T22:59:00Z"
      },
      "messageType": "M2"
    },
    {
      "id": "5WVM44PJ",
      "riskyWindow": {
        "from": "2021-07-25T00:00:00Z",
        "until": "2021-07-25T22:59:00Z"
      },
      "messageType": "M2"
    },
    {
      "id": "RP9X4239",
      "riskyWindow": {
        "from": "2021-07-24T00:00:00Z",
        "until": "2021-07-24T22:59:00Z"
      },
      "messageType": "M2"
    },
    {
      "id": "54VWXJM5",
      "riskyWindow": {
        "from": "2021-07-25T00:00:00Z",
        "until": "2021-07-25T22:59:00Z"
      },
      "messageType": "M2"
    },
    {
      "id": "RJ69389R",
      "riskyWindow": {
        "from": "2021-07-25T00:00:00Z",
        "until": "2021-07-25T22:59:00Z"
      },
      "messageType": "M2"
    },
    {
      "id": "53WPKXX6",
      "riskyWindow": {
        "from": "2021-07-27T00:00:00Z",
        "until": "2021-07-27T22:59:00Z"
      },
      "messageType": "M2"
    },
    {
      "id": "4RKK96RY",
      "riskyWindow": {
        "from": "2021-07-25T00:00:00Z",
        "until": "2021-07-25T22:59:00Z"
      },
      "messageType": "M2"
    },
    {
      "id": "54283MVV",
      "riskyWindow": {
        "from": "2021-07-24T00:00:00Z",
        "until": "2021-07-24T22:59:00Z"
      },
      "messageType": "M2"
    },
    {
      "id": "5Y9WMK6W",
      "riskyWindow": {
        "from": "2021-07-24T00:00:00Z",
        "until": "2021-07-24T22:59:00Z"
      },
      "messageType": "M2"
    },
    {
      "id": "RKY44896",
      "riskyWindow": {
        "from": "2021-07-25T00:00:00Z",
        "until": "2021-07-25T22:59:00Z"
      },
      "messageType": "M2"
    },
    {
      "id": "5X8X42Y5",
      "riskyWindow": {
        "from": "2021-07-26T00:00:00Z",
        "until": "2021-07-26T22:59:00Z"
      },
      "messageType": "M2"
    },
    {
      "id": "5WXWWMMR",
      "riskyWindow": {
        "from": "2021-07-24T00:00:00Z",
        "until": "2021-07-24T22:59:00Z"
      },
      "messageType": "M2"
    },
    {
      "id": "V5MW86K5",
      "riskyWindow": {
        "from": "2021-07-25T00:00:00Z",
        "until": "2021-07-25T22:59:00Z"
      },
      "messageType": "M2"
    },
    {
      "id": "R9J39WM6",
      "riskyWindow": {
        "from": "2021-07-25T00:00:00Z",
        "until": "2021-07-25T22:59:00Z"
      },
      "messageType": "M2"
    },
    {
      "id": "RKYW4V46",
      "riskyWindow": {
        "from": "2021-07-24T00:00:00Z",
        "until": "2021-07-24T22:59:00Z"
      },
      "messageType": "M2"
    },
    {
      "id": "533PVP45",
      "riskyWindow": {
        "from": "2021-07-26T00:00:00Z",
        "until": "2021-07-26T22:59:00Z"
      },
      "messageType": "M2"
    },
    {
      "id": "R8V3386M",
      "riskyWindow": {
        "from": "2021-07-25T00:00:00Z",
        "until": "2021-07-25T22:59:00Z"
      },
      "messageType": "M2"
    },
    {
      "id": "5W8V3MMR",
      "riskyWindow": {
        "from": "2021-07-25T23:00:00Z",
        "until": "2021-07-26T22:59:59Z"
      },
      "messageType": "M2"
    },
    {
      "id": "RP9VWYV5",
      "riskyWindow": {
        "from": "2021-07-25T00:00:00Z",
        "until": "2021-07-25T22:59:00Z"
      },
      "messageType": "M2"
    },
    {
      "id": "544298V5",
      "riskyWindow": {
        "from": "2021-07-24T00:00:00Z",
        "until": "2021-07-24T22:59:00Z"
      },
      "messageType": "M2"
    },
    {
      "id": "533MV9W5",
      "riskyWindow": {
        "from": "2021-07-26T00:00:00Z",
        "until": "2021-07-26T22:59:00Z"
      },
      "messageType": "M2"
    },
    {
      "id": "528W2KK5",
      "riskyWindow": {
        "from": "2021-07-24T00:00:00Z",
        "until": "2021-07-24T22:59:00Z"
      },
      "messageType": "M2"
    },
    {
      "id": "562JWMX5",
      "riskyWindow": {
        "from": "2021-07-26T23:00:00Z",
        "until": "2021-07-27T22:59:59Z"
      },
      "messageType": "M2"
    },
    {
      "id": "RKY823M2",
      "riskyWindow": {
        "from": "2021-07-24T00:00:00Z",
        "until": "2021-07-24T22:59:00Z"
      },
      "messageType": "M2"
    },
    {
      "id": "RJV9499V",
      "riskyWindow": {
        "from": "2021-07-25T00:00:00Z",
        "until": "2021-07-25T22:59:00Z"
      },
      "messageType": "M2"
    },
    {
      "id": "5W32J3J5",
      "riskyWindow": {
        "from": "2021-07-26T00:00:00Z",
        "until": "2021-07-26T22:59:00Z"
      },
      "messageType": "M2"
    },
    {
      "id": "5VX44V4P",
      "riskyWindow": {
        "from": "2021-07-25T23:00:00Z",
        "until": "2021-07-26T22:59:59Z"
      },
      "messageType": "M2"
    },
    {
      "id": "RPV948JR",
      "riskyWindow": {
        "from": "2021-07-24T00:00:00Z",
        "until": "2021-07-24T22:59:00Z"
      },
      "messageType": "M2"
    },
    {
      "id": "54YM8YMR",
      "riskyWindow": {
        "from": "2021-07-24T00:00:00Z",
        "until": "2021-07-24T22:59:00Z"
      },
      "messageType": "M2"
    },
    {
      "id": "532PXXJR",
      "riskyWindow": {
        "from": "2021-07-24T00:00:00Z",
        "until": "2021-07-24T22:59:00Z"
      },
      "messageType": "M2"
    },
    {
      "id": "RKYXMMP4",
      "riskyWindow": {
        "from": "2021-07-24T00:00:00Z",
        "until": "2021-07-24T22:59:00Z"
      },
      "messageType": "M2"
    },
    {
      "id": "RJVJY9K2",
      "riskyWindow": {
        "from": "2021-07-24T00:00:00Z",
        "until": "2021-07-24T22:59:00Z"
      },
      "messageType": "M2"
    },
    {
      "id": "RKM9KW8R",
      "riskyWindow": {
        "from": "2021-07-26T23:00:00Z",
        "until": "2021-07-27T22:59:59Z"
      },
      "messageType": "M2"
    },
    {
      "id": "52VY9V45",
      "riskyWindow": {
        "from": "2021-07-24T00:00:00Z",
        "until": "2021-07-24T22:59:00Z"
      },
      "messageType": "M2"
    },
    {
      "id": "RKYY2PW3",
      "riskyWindow": {
        "from": "2021-07-24T00:00:00Z",
        "until": "2021-07-24T22:59:00Z"
      },
      "messageType": "M2"
    },
    {
      "id": "5X24JK85",
      "riskyWindow": {
        "from": "2021-07-24T00:00:00Z",
        "until": "2021-07-24T22:59:00Z"
      },
      "messageType": "M2"
    },
    {
      "id": "5Y96JVMM",
      "riskyWindow": {
        "from": "2021-07-24T00:00:00Z",
        "until": "2021-07-24T22:59:00Z"
      },
      "messageType": "M2"
    },
    {
      "id": "52WPJXY8",
      "riskyWindow": {
        "from": "2021-07-24T00:00:00Z",
        "until": "2021-07-24T22:59:00Z"
      },
      "messageType": "M2"
    },
    {
      "id": "5M39X9Y5",
      "riskyWindow": {
        "from": "2021-07-24T00:00:00Z",
        "until": "2021-07-24T22:59:00Z"
      },
      "messageType": "M2"
    },
    {
      "id": "R9JK9Y4X",
      "riskyWindow": {
        "from": "2021-07-24T00:00:00Z",
        "until": "2021-07-24T22:59:00Z"
      },
      "messageType": "M2"
    },
    {
      "id": "RJ6823VR",
      "riskyWindow": {
        "from": "2021-07-24T00:00:00Z",
        "until": "2021-07-24T22:59:00Z"
      },
      "messageType": "M2"
    },
    {
      "id": "5MW69Y6X",
      "riskyWindow": {
        "from": "2021-07-24T00:00:00Z",
        "until": "2021-07-24T22:59:00Z"
      },
      "messageType": "M2"
    },
    {
      "id": "5W34V4W5",
      "riskyWindow": {
        "from": "2021-07-25T00:00:00Z",
        "until": "2021-07-25T22:59:00Z"
      },
      "messageType": "M2"
    },
    {
      "id": "RJ8VPKVR",
      "riskyWindow": {
        "from": "2021-07-25T00:00:00Z",
        "until": "2021-07-25T22:59:00Z"
      },
      "messageType": "M2"
    },
    {
      "id": "5M4K6Y9R",
      "riskyWindow": {
        "from": "2021-07-24T00:00:00Z",
        "until": "2021-07-24T22:59:00Z"
      },
      "messageType": "M2"
    },
    {
      "id": "R9M8MKXR",
      "riskyWindow": {
        "from": "2021-07-24T00:00:00Z",
        "until": "2021-07-24T22:59:00Z"
      },
      "messageType": "M2"
    },
    {
      "id": "544JVX45",
      "riskyWindow": {
        "from": "2021-07-24T00:00:00Z",
        "until": "2021-07-24T22:59:00Z"
      },
      "messageType": "M2"
    },
    {
      "id": "R9JXV642",
      "riskyWindow": {
        "from": "2021-07-24T00:00:00Z",
        "until": "2021-07-24T22:59:00Z"
      },
      "messageType": "M2"
    },
    {
      "id": "R9JX8KX6",
      "riskyWindow": {
        "from": "2021-07-25T00:00:00Z",
        "until": "2021-07-25T22:59:00Z"
      },
      "messageType": "M2"
    },
    {
      "id": "RK3W923R",
      "riskyWindow": {
        "from": "2021-07-24T00:00:00Z",
        "until": "2021-07-24T22:59:00Z"
      },
      "messageType": "M2"
    },
    {
      "id": "5Y6JY2WR",
      "riskyWindow": {
        "from": "2021-07-24T00:00:00Z",
        "until": "2021-07-24T22:59:00Z"
      },
      "messageType": "M2"
    },
    {
      "id": "53WMKW34",
      "riskyWindow": {
        "from": "2021-07-24T00:00:00Z",
        "until": "2021-07-24T22:59:00Z"
      },
      "messageType": "M2"
    },
    {
      "id": "R996VWVR",
      "riskyWindow": {
        "from": "2021-07-24T00:00:00Z",
        "until": "2021-07-24T22:59:00Z"
      },
      "messageType": "M2"
    },
    {
      "id": "R99JWJ2R",
      "riskyWindow": {
        "from": "2021-07-24T00:00:00Z",
        "until": "2021-07-24T22:59:00Z"
      },
      "messageType": "M2"
    },
    {
      "id": "R86KJ68R",
      "riskyWindow": {
        "from": "2021-07-24T00:00:00Z",
        "until": "2021-07-24T22:59:00Z"
      },
      "messageType": "M2"
    },
    {
      "id": "5384K6JR",
      "riskyWindow": {
        "from": "2021-07-26T00:00:00Z",
        "until": "2021-07-26T22:59:00Z"
      },
      "messageType": "M2"
    },
    {
      "id": "RJV6342W",
      "riskyWindow": {
        "from": "2021-07-25T23:00:00Z",
        "until": "2021-07-26T22:59:59Z"
      },
      "messageType": "M2"
    },
    {
      "id": "5VXKXX95",
      "riskyWindow": {
        "from": "2021-07-25T00:00:00Z",
        "until": "2021-07-25T22:59:00Z"
      },
      "messageType": "M2"
    },
    {
      "id": "5X88W285",
      "riskyWindow": {
        "from": "2021-07-24T00:00:00Z",
        "until": "2021-07-24T22:59:00Z"
      },
      "messageType": "M2"
    },
    {
      "id": "5VX2YJWP",
      "riskyWindow": {
        "from": "2021-07-25T00:00:00Z",
        "until": "2021-07-25T22:59:00Z"
      },
      "messageType": "M2"
    },
    {
      "id": "5YP2V6PR",
      "riskyWindow": {
        "from": "2021-07-25T00:00:00Z",
        "until": "2021-07-25T22:59:00Z"
      },
      "messageType": "M2"
    },
    {
      "id": "5Y9Y8WX5",
      "riskyWindow": {
        "from": "2021-07-25T23:00:00Z",
        "until": "2021-07-26T22:59:59Z"
      },
      "messageType": "M2"
    },
    {
      "id": "5Y9WP92P",
      "riskyWindow": {
        "from": "2021-07-24T00:00:00Z",
        "until": "2021-07-24T22:59:00Z"
      },
      "messageType": "M2"
    },
    {
      "id": "5424MY33",
      "riskyWindow": {
        "from": "2021-07-25T00:00:00Z",
        "until": "2021-07-25T22:59:00Z"
      },
      "messageType": "M2"
    },
    {
      "id": "RK2MMY85",
      "riskyWindow": {
        "from": "2021-07-25T00:00:00Z",
        "until": "2021-07-25T22:59:00Z"
      },
      "messageType": "M2"
    },
    {
      "id": "5Y3K62Y5",
      "riskyWindow": {
        "from": "2021-07-25T00:00:00Z",
        "until": "2021-07-25T22:59:00Z"
      },
      "messageType": "M2"
    },
    {
      "id": "RP9KY6K5",
      "riskyWindow": {
        "from": "2021-07-27T00:00:00Z",
        "until": "2021-07-27T22:59:00Z"
      },
      "messageType": "M2"
    },
    {
      "id": "5264VMP5",
      "riskyWindow": {
        "from": "2021-07-25T23:00:00Z",
        "until": "2021-07-26T22:59:59Z"
      },
      "messageType": "M2"
    },
    {
      "id": "R8VW24MR",
      "riskyWindow": {
        "from": "2021-07-24T00:00:00Z",
        "until": "2021-07-24T22:59:00Z"
      },
      "messageType": "M2"
    },
    {
      "id": "533PJ925",
      "riskyWindow": {
        "from": "2021-07-24T00:00:00Z",
        "until": "2021-07-24T22:59:00Z"
      },
      "messageType": "M2"
    },
    {
      "id": "52W96Y94",
      "riskyWindow": {
        "from": "2021-07-25T00:00:00Z",
        "until": "2021-07-25T22:59:00Z"
      },
      "messageType": "M2"
    },
    {
      "id": "R9YKJVXR",
      "riskyWindow": {
        "from": "2021-07-26T00:00:00Z",
        "until": "2021-07-26T22:59:00Z"
      },
      "messageType": "M2"
    },
    {
      "id": "R99JPYYR",
      "riskyWindow": {
        "from": "2021-07-25T00:00:00Z",
        "until": "2021-07-25T22:59:00Z"
      },
      "messageType": "M2"
    },
    {
      "id": "52W26WVX",
      "riskyWindow": {
        "from": "2021-07-24T00:00:00Z",
        "until": "2021-07-24T22:59:00Z"
      },
      "messageType": "M2"
    },
    {
      "id": "53W2XV62",
      "riskyWindow": {
        "from": "2021-07-26T00:00:00Z",
        "until": "2021-07-26T22:59:00Z"
      },
      "messageType": "M2"
    },
    {
      "id": "RJXY89WR",
      "riskyWindow": {
        "from": "2021-07-24T00:00:00Z",
        "until": "2021-07-24T22:59:00Z"
      },
      "messageType": "M2"
    },
    {
      "id": "5WX826JR",
      "riskyWindow": {
        "from": "2021-07-24T00:00:00Z",
        "until": "2021-07-24T22:59:00Z"
      },
      "messageType": "M2"
    },
    {
      "id": "5WJ884WR",
      "riskyWindow": {
        "from": "2021-07-26T00:00:00Z",
        "until": "2021-07-26T22:59:00Z"
      },
      "messageType": "M2"
    },
    {
      "id": "542PMPV5",
      "riskyWindow": {
        "from": "2021-07-25T00:00:00Z",
        "until": "2021-07-25T22:59:00Z"
      },
      "messageType": "M2"
    },
    {
      "id": "M53VJKVR",
      "riskyWindow": {
        "from": "2021-07-26T23:00:00Z",
        "until": "2021-07-27T22:59:59Z"
      },
      "messageType": "M2"
    },
    {
      "id": "5Y9JJ6W5",
      "riskyWindow": {
        "from": "2021-07-24T00:00:00Z",
        "until": "2021-07-24T22:59:00Z"
      },
      "messageType": "M2"
    },
    {
      "id": "5V63WJY5",
      "riskyWindow": {
        "from": "2021-07-24T00:00:00Z",
        "until": "2021-07-24T22:59:00Z"
      },
      "messageType": "M2"
    },
    {
      "id": "53W2K2VJ",
      "riskyWindow": {
        "from": "2021-07-24T00:00:00Z",
        "until": "2021-07-24T22:59:00Z"
      },
      "messageType": "M2"
    },
    {
      "id": "R9JKJVM9",
      "riskyWindow": {
        "from": "2021-07-24T00:00:00Z",
        "until": "2021-07-24T22:59:00Z"
      },
      "messageType": "M2"
    },
    {
      "id": "RKY64M6R",
      "riskyWindow": {
        "from": "2021-07-24T00:00:00Z",
        "until": "2021-07-24T22:59:00Z"
      },
      "messageType": "M2"
    },
    {
      "id": "RK6M3V65",
      "riskyWindow": {
        "from": "2021-07-24T00:00:00Z",
        "until": "2021-07-24T22:59:00Z"
      },
      "messageType": "M2"
    },
    {
      "id": "RJM89895",
      "riskyWindow": {
        "from": "2021-07-24T00:00:00Z",
        "until": "2021-07-24T22:59:00Z"
      },
      "messageType": "M2"
    },
    {
      "id": "RP934436",
      "riskyWindow": {
        "from": "2021-07-24T00:00:00Z",
        "until": "2021-07-24T22:59:00Z"
      },
      "messageType": "M2"
    },
    {
      "id": "5YPJWPMR",
      "riskyWindow": {
        "from": "2021-07-24T00:00:00Z",
        "until": "2021-07-24T22:59:00Z"
      },
      "messageType": "M2"
    },
    {
      "id": "R9J2PMX5",
      "riskyWindow": {
        "from": "2021-07-25T00:00:00Z",
        "until": "2021-07-25T22:59:00Z"
      },
      "messageType": "M2"
    },
    {
      "id": "5VX9MMJ4",
      "riskyWindow": {
        "from": "2021-07-25T00:00:00Z",
        "until": "2021-07-25T22:59:00Z"
      },
      "messageType": "M2"
    },
    {
      "id": "RJV3Y3W2",
      "riskyWindow": {
        "from": "2021-07-24T00:00:00Z",
        "until": "2021-07-24T22:59:00Z"
      },
      "messageType": "M2"
    },
    {
      "id": "R9M6K4VR",
      "riskyWindow": {
        "from": "2021-07-24T00:00:00Z",
        "until": "2021-07-24T22:59:00Z"
      },
      "messageType": "M2"
    },
    {
      "id": "5WWW2VP5",
      "riskyWindow": {
        "from": "2021-07-25T00:00:00Z",
        "until": "2021-07-25T22:59:00Z"
      },
      "messageType": "M2"
    },
    {
      "id": "566M6MY5",
      "riskyWindow": {
        "from": "2021-07-25T00:00:00Z",
        "until": "2021-07-25T22:59:00Z"
      },
      "messageType": "M2"
    },
    {
      "id": "54946VMR",
      "riskyWindow": {
        "from": "2021-07-25T23:00:00Z",
        "until": "2021-07-26T22:59:59Z"
      },
      "messageType": "M2"
    },
    {
      "id": "56KPVMXR",
      "riskyWindow": {
        "from": "2021-07-25T23:00:00Z",
        "until": "2021-07-26T22:59:59Z"
      },
      "messageType": "M2"
    },
    {
      "id": "R9JPY825",
      "riskyWindow": {
        "from": "2021-07-26T23:00:00Z",
        "until": "2021-07-27T22:59:59Z"
      },
      "messageType": "M2"
    },
    {
      "id": "52X92MK5",
      "riskyWindow": {
        "from": "2021-07-25T00:00:00Z",
        "until": "2021-07-25T22:59:00Z"
      },
      "messageType": "M2"
    },
    {
      "id": "56838PJX",
      "riskyWindow": {
        "from": "2021-07-26T00:00:00Z",
        "until": "2021-07-26T22:59:00Z"
      },
      "messageType": "M2"
    },
    {
      "id": "5VXPY6X8",
      "riskyWindow": {
        "from": "2021-07-24T00:00:00Z",
        "until": "2021-07-24T22:59:00Z"
      },
      "messageType": "M2"
    },
    {
      "id": "5444V9Y5",
      "riskyWindow": {
        "from": "2021-07-25T00:00:00Z",
        "until": "2021-07-25T22:59:00Z"
      },
      "messageType": "M2"
    },
    {
      "id": "R8V3YY6R",
      "riskyWindow": {
        "from": "2021-07-24T00:00:00Z",
        "until": "2021-07-24T22:59:00Z"
      },
      "messageType": "M2"
    },
    {
      "id": "5W4XYWXR",
      "riskyWindow": {
        "from": "2021-07-27T00:00:00Z",
        "until": "2021-07-27T22:59:00Z"
      },
      "messageType": "M2"
    },
    {
      "id": "R9JKW366",
      "riskyWindow": {
        "from": "2021-07-25T00:00:00Z",
        "until": "2021-07-25T22:59:00Z"
      },
      "messageType": "M2"
    },
    {
      "id": "5XKM923R",
      "riskyWindow": {
        "from": "2021-07-24T00:00:00Z",
        "until": "2021-07-24T22:59:00Z"
      },
      "messageType": "M2"
    },
    {
      "id": "56928YMR",
      "riskyWindow": {
        "from": "2021-07-25T00:00:00Z",
        "until": "2021-07-25T22:59:00Z"
      },
      "messageType": "M2"
    },
    {
      "id": "568X34YX",
      "riskyWindow": {
        "from": "2021-07-25T23:00:00Z",
        "until": "2021-07-26T22:59:59Z"
      },
      "messageType": "M2"
    },
    {
      "id": "X5YKP8X5",
      "riskyWindow": {
        "from": "2021-07-24T00:00:00Z",
        "until": "2021-07-24T22:59:00Z"
      },
      "messageType": "M2"
    },
    {
      "id": "52WVM4M8",
      "riskyWindow": {
        "from": "2021-07-24T00:00:00Z",
        "until": "2021-07-24T22:59:00Z"
      },
      "messageType": "M2"
    },
    {
      "id": "5Y69X4MR",
      "riskyWindow": {
        "from": "2021-07-24T00:00:00Z",
        "until": "2021-07-24T22:59:00Z"
      },
      "messageType": "M2"
    },
    {
      "id": "539JXWV5",
      "riskyWindow": {
        "from": "2021-07-25T00:00:00Z",
        "until": "2021-07-25T22:59:00Z"
      },
      "messageType": "M2"
    },
    {
      "id": "R9M8XWPR",
      "riskyWindow": {
        "from": "2021-07-25T00:00:00Z",
        "until": "2021-07-25T22:59:00Z"
      },
      "messageType": "M2"
    },
    {
      "id": "5XKWMJYR",
      "riskyWindow": {
        "from": "2021-07-24T00:00:00Z",
        "until": "2021-07-24T22:59:00Z"
      },
      "messageType": "M2"
    },
    {
      "id": "RK8M4V45",
      "riskyWindow": {
        "from": "2021-07-24T00:00:00Z",
        "until": "2021-07-24T22:59:00Z"
      },
      "messageType": "M2"
    },
    {
      "id": "5WM8YVX5",
      "riskyWindow": {
        "from": "2021-07-24T00:00:00Z",
        "until": "2021-07-24T22:59:00Z"
      },
      "messageType": "M2"
    },
    {
      "id": "R8JYK3KR",
      "riskyWindow": {
        "from": "2021-07-24T00:00:00Z",
        "until": "2021-07-24T22:59:00Z"
      },
      "messageType": "M2"
    },
    {
      "id": "53W2268W",
      "riskyWindow": {
        "from": "2021-07-25T00:00:00Z",
        "until": "2021-07-25T22:59:00Z"
      },
      "messageType": "M2"
    },
    {
      "id": "RKJ6X6M5",
      "riskyWindow": {
        "from": "2021-07-25T00:00:00Z",
        "until": "2021-07-25T22:59:00Z"
      },
      "messageType": "M2"
    },
    {
      "id": "5X84JJ35",
      "riskyWindow": {
        "from": "2021-07-24T00:00:00Z",
        "until": "2021-07-24T22:59:00Z"
      },
      "messageType": "M2"
    },
    {
      "id": "52V9YMK5",
      "riskyWindow": {
        "from": "2021-07-24T00:00:00Z",
        "until": "2021-07-24T22:59:00Z"
      },
      "messageType": "M2"
    },
    {
      "id": "5M4PM9VR",
      "riskyWindow": {
        "from": "2021-07-26T00:00:00Z",
        "until": "2021-07-26T22:59:00Z"
      },
      "messageType": "M2"
    },
    {
      "id": "5Y9J9295",
      "riskyWindow": {
        "from": "2021-07-24T00:00:00Z",
        "until": "2021-07-24T22:59:00Z"
      },
      "messageType": "M2"
    },
    {
      "id": "V5VY89PR",
      "riskyWindow": {
        "from": "2021-07-25T00:00:00Z",
        "until": "2021-07-25T22:59:00Z"
      },
      "messageType": "M2"
    },
    {
      "id": "RP66KV9R",
      "riskyWindow": {
        "from": "2021-07-25T00:00:00Z",
        "until": "2021-07-25T22:59:00Z"
      },
      "messageType": "M2"
    },
    {
      "id": "5WPMKJWR",
      "riskyWindow": {
        "from": "2021-07-24T00:00:00Z",
        "until": "2021-07-24T22:59:00Z"
      },
      "messageType": "M2"
    },
    {
      "id": "52WWX94R",
      "riskyWindow": {
        "from": "2021-07-25T00:00:00Z",
        "until": "2021-07-25T22:59:00Z"
      },
      "messageType": "M2"
    },
    {
      "id": "52WPM4KX",
      "riskyWindow": {
        "from": "2021-07-24T00:00:00Z",
        "until": "2021-07-24T22:59:00Z"
      },
      "messageType": "M2"
    },
    {
      "id": "RP9JP3PV",
      "riskyWindow": {
        "from": "2021-07-24T00:00:00Z",
        "until": "2021-07-24T22:59:00Z"
      },
      "messageType": "M2"
    },
    {
      "id": "52W33J28",
      "riskyWindow": {
        "from": "2021-07-25T00:00:00Z",
        "until": "2021-07-25T22:59:00Z"
      },
      "messageType": "M2"
    },
    {
      "id": "5Y9KM9M8",
      "riskyWindow": {
        "from": "2021-07-24T23:00:00Z",
        "until": "2021-07-25T22:59:59Z"
      },
      "messageType": "M2"
    },
    {
      "id": "RP988J8V",
      "riskyWindow": {
        "from": "2021-07-24T00:00:00Z",
        "until": "2021-07-24T22:59:00Z"
      },
      "messageType": "M2"
    },
    {
      "id": "RKJJ8445",
      "riskyWindow": {
        "from": "2021-07-25T00:00:00Z",
        "until": "2021-07-25T22:59:00Z"
      },
      "messageType": "M2"
    },
    {
      "id": "5XMXP6YR",
      "riskyWindow": {
        "from": "2021-07-24T23:00:00Z",
        "until": "2021-07-25T22:59:59Z"
      },
      "messageType": "M2"
    },
    {
      "id": "RP9PP6PX",
      "riskyWindow": {
        "from": "2021-07-25T00:00:00Z",
        "until": "2021-07-25T22:59:00Z"
      },
      "messageType": "M2"
    },
    {
      "id": "5YXJXJYR",
      "riskyWindow": {
        "from": "2021-07-26T00:00:00Z",
        "until": "2021-07-26T22:59:00Z"
      },
      "messageType": "M2"
    },
    {
      "id": "RJVM2922",
      "riskyWindow": {
        "from": "2021-07-24T00:00:00Z",
        "until": "2021-07-24T22:59:00Z"
      },
      "messageType": "M2"
    },
    {
      "id": "5XX3JMY5",
      "riskyWindow": {
        "from": "2021-07-24T00:00:00Z",
        "until": "2021-07-24T22:59:00Z"
      },
      "messageType": "M2"
    },
    {
      "id": "56829M6M",
      "riskyWindow": {
        "from": "2021-07-24T00:00:00Z",
        "until": "2021-07-24T22:59:00Z"
      },
      "messageType": "M2"
    },
    {
      "id": "568V238J",
      "riskyWindow": {
        "from": "2021-07-25T00:00:00Z",
        "until": "2021-07-25T22:59:00Z"
      },
      "messageType": "M2"
    },
    {
      "id": "5WV8438R",
      "riskyWindow": {
        "from": "2021-07-24T00:00:00Z",
        "until": "2021-07-24T22:59:00Z"
      },
      "messageType": "M2"
    },
    {
      "id": "538J39VR",
      "riskyWindow": {
        "from": "2021-07-24T00:00:00Z",
        "until": "2021-07-24T22:59:00Z"
      },
      "messageType": "M2"
    },
    {
      "id": "RP23YXVR",
      "riskyWindow": {
        "from": "2021-07-26T00:00:00Z",
        "until": "2021-07-26T22:59:00Z"
      },
      "messageType": "M2"
    },
    {
      "id": "5VXPK945",
      "riskyWindow": {
        "from": "2021-07-25T00:00:00Z",
        "until": "2021-07-25T22:59:00Z"
      },
      "messageType": "M2"
    },
    {
      "id": "R9926KPR",
      "riskyWindow": {
        "from": "2021-07-24T00:00:00Z",
        "until": "2021-07-24T22:59:00Z"
      },
      "messageType": "M2"
    },
    {
      "id": "52KKPYPR",
      "riskyWindow": {
        "from": "2021-07-25T23:00:00Z",
        "until": "2021-07-26T22:59:59Z"
      },
      "messageType": "M2"
    },
    {
      "id": "RJ936J25",
      "riskyWindow": {
        "from": "2021-07-24T00:00:00Z",
        "until": "2021-07-24T22:59:00Z"
      },
      "messageType": "M2"
    },
    {
      "id": "RJ2M8K6R",
      "riskyWindow": {
        "from": "2021-07-24T00:00:00Z",
        "until": "2021-07-24T22:59:00Z"
      },
      "messageType": "M2"
    },
    {
      "id": "53VP92VR",
      "riskyWindow": {
        "from": "2021-07-25T00:00:00Z",
        "until": "2021-07-25T22:59:00Z"
      },
      "messageType": "M2"
    },
    {
      "id": "528PW485",
      "riskyWindow": {
        "from": "2021-07-24T00:00:00Z",
        "until": "2021-07-24T22:59:00Z"
      },
      "messageType": "M2"
    },
    {
      "id": "539VXKY5",
      "riskyWindow": {
        "from": "2021-07-24T00:00:00Z",
        "until": "2021-07-24T22:59:00Z"
      },
      "messageType": "M2"
    },
    {
      "id": "5X2VK42W",
      "riskyWindow": {
        "from": "2021-07-24T23:00:00Z",
        "until": "2021-07-25T22:59:59Z"
      },
      "messageType": "M2"
    },
    {
      "id": "R8VKY84M",
      "riskyWindow": {
        "from": "2021-07-24T00:00:00Z",
        "until": "2021-07-24T22:59:00Z"
      },
      "messageType": "M2"
    },
    {
      "id": "RJ2VP48R",
      "riskyWindow": {
        "from": "2021-07-24T00:00:00Z",
        "until": "2021-07-24T22:59:00Z"
      },
      "messageType": "M2"
    },
    {
      "id": "P52MPJ9R",
      "riskyWindow": {
        "from": "2021-07-26T00:00:00Z",
        "until": "2021-07-26T22:59:00Z"
      },
      "messageType": "M2"
    },
    {
      "id": "53WPKKJY",
      "riskyWindow": {
        "from": "2021-07-24T00:00:00Z",
        "until": "2021-07-24T22:59:00Z"
      },
      "messageType": "M2"
    },
    {
      "id": "5XVVKYY5",
      "riskyWindow": {
        "from": "2021-07-25T00:00:00Z",
        "until": "2021-07-25T22:59:00Z"
      },
      "messageType": "M2"
    },
    {
      "id": "5WV6P86J",
      "riskyWindow": {
        "from": "2021-07-24T00:00:00Z",
        "until": "2021-07-24T22:59:00Z"
      },
      "messageType": "M2"
    },
    {
      "id": "5MPM4VYR",
      "riskyWindow": {
        "from": "2021-07-25T00:00:00Z",
        "until": "2021-07-25T22:59:00Z"
      },
      "messageType": "M2"
    },
    {
      "id": "R8PY8PMR",
      "riskyWindow": {
        "from": "2021-07-25T00:00:00Z",
        "until": "2021-07-25T22:59:00Z"
      },
      "messageType": "M2"
    },
    {
      "id": "52W8KPXR",
      "riskyWindow": {
        "from": "2021-07-26T00:00:00Z",
        "until": "2021-07-26T22:59:00Z"
      },
      "messageType": "M2"
    },
    {
      "id": "RP9P89YK",
      "riskyWindow": {
        "from": "2021-07-24T00:00:00Z",
        "until": "2021-07-24T22:59:00Z"
      },
      "messageType": "M2"
    },
    {
      "id": "5Y9JY6W5",
      "riskyWindow": {
        "from": "2021-07-24T00:00:00Z",
        "until": "2021-07-24T22:59:00Z"
      },
      "messageType": "M2"
    },
    {
      "id": "5XKYP2YR",
      "riskyWindow": {
        "from": "2021-07-24T00:00:00Z",
        "until": "2021-07-24T22:59:00Z"
      },
      "messageType": "M2"
    },
    {
      "id": "KRPJWVVR",
      "riskyWindow": {
        "from": "2021-07-26T00:00:00Z",
        "until": "2021-07-26T22:59:00Z"
      },
      "messageType": "M2"
    },
    {
      "id": "RJY3XVV5",
      "riskyWindow": {
        "from": "2021-07-25T00:00:00Z",
        "until": "2021-07-25T22:59:00Z"
      },
      "messageType": "M2"
    },
    {
      "id": "5YK99VX5",
      "riskyWindow": {
        "from": "2021-07-24T00:00:00Z",
        "until": "2021-07-24T22:59:00Z"
      },
      "messageType": "M2"
    },
    {
      "id": "5WVVP24P",
      "riskyWindow": {
        "from": "2021-07-24T00:00:00Z",
        "until": "2021-07-24T22:59:00Z"
      },
      "messageType": "M2"
    },
    {
      "id": "5Y99X2P5",
      "riskyWindow": {
        "from": "2021-07-24T00:00:00Z",
        "until": "2021-07-24T22:59:00Z"
      },
      "messageType": "M2"
    },
    {
      "id": "RKYXY2P3",
      "riskyWindow": {
        "from": "2021-07-24T00:00:00Z",
        "until": "2021-07-24T22:59:00Z"
      },
      "messageType": "M2"
    },
    {
      "id": "5Y4VK9WR",
      "riskyWindow": {
        "from": "2021-07-24T23:00:00Z",
        "until": "2021-07-25T22:59:59Z"
      },
      "messageType": "M2"
    },
    {
      "id": "M53W2WY5",
      "riskyWindow": {
        "from": "2021-07-24T00:00:00Z",
        "until": "2021-07-24T22:59:00Z"
      },
      "messageType": "M2"
    },
    {
      "id": "RP9J3922",
      "riskyWindow": {
        "from": "2021-07-24T00:00:00Z",
        "until": "2021-07-24T22:59:00Z"
      },
      "messageType": "M2"
    },
    {
      "id": "V5MWWW95",
      "riskyWindow": {
        "from": "2021-07-24T00:00:00Z",
        "until": "2021-07-24T22:59:00Z"
      },
      "messageType": "M2"
    },
    {
      "id": "R8PJKP8R",
      "riskyWindow": {
        "from": "2021-07-25T00:00:00Z",
        "until": "2021-07-25T22:59:00Z"
      },
      "messageType": "M2"
    },
    {
      "id": "5XVJ6P85",
      "riskyWindow": {
        "from": "2021-07-25T00:00:00Z",
        "until": "2021-07-25T22:59:00Z"
      },
      "messageType": "M2"
    },
    {
      "id": "5VK4364R",
      "riskyWindow": {
        "from": "2021-07-24T00:00:00Z",
        "until": "2021-07-24T22:59:00Z"
      },
      "messageType": "M2"
    },
    {
      "id": "5W8PWXPR",
      "riskyWindow": {
        "from": "2021-07-24T00:00:00Z",
        "until": "2021-07-24T22:59:00Z"
      },
      "messageType": "M2"
    },
    {
      "id": "RKY2K332",
      "riskyWindow": {
        "from": "2021-07-25T00:00:00Z",
        "until": "2021-07-25T22:59:00Z"
      },
      "messageType": "M2"
    },
    {
      "id": "52KW4M8R",
      "riskyWindow": {
        "from": "2021-07-24T23:00:00Z",
        "until": "2021-07-25T22:59:59Z"
      },
      "messageType": "M2"
    },
    {
      "id": "5X22KW35",
      "riskyWindow": {
        "from": "2021-07-24T23:00:00Z",
        "until": "2021-07-25T22:59:59Z"
      },
      "messageType": "M2"
    },
    {
      "id": "54XWWM45",
      "riskyWindow": {
        "from": "2021-07-24T00:00:00Z",
        "until": "2021-07-24T22:59:00Z"
      },
      "messageType": "M2"
    },
    {
      "id": "5YXYVPXR",
      "riskyWindow": {
        "from": "2021-07-24T00:00:00Z",
        "until": "2021-07-24T22:59:00Z"
      },
      "messageType": "M2"
    },
    {
      "id": "568P3W95",
      "riskyWindow": {
        "from": "2021-07-25T00:00:00Z",
        "until": "2021-07-25T22:59:00Z"
      },
      "messageType": "M2"
    },
    {
      "id": "RJVMJV6R",
      "riskyWindow": {
        "from": "2021-07-24T00:00:00Z",
        "until": "2021-07-24T22:59:00Z"
      },
      "messageType": "M2"
    },
    {
      "id": "5WYP6VP5",
      "riskyWindow": {
        "from": "2021-07-24T23:00:00Z",
        "until": "2021-07-25T22:59:59Z"
      },
      "messageType": "M2"
    },
    {
      "id": "R9Y2V6PR",
      "riskyWindow": {
        "from": "2021-07-26T00:00:00Z",
        "until": "2021-07-26T22:59:00Z"
      },
      "messageType": "M2"
    },
    {
      "id": "R9MKJ46R",
      "riskyWindow": {
        "from": "2021-07-24T00:00:00Z",
        "until": "2021-07-24T22:59:00Z"
      },
      "messageType": "M2"
    },
    {
      "id": "RP9XW29X",
      "riskyWindow": {
        "from": "2021-07-24T00:00:00Z",
        "until": "2021-07-24T22:59:00Z"
      },
      "messageType": "M2"
    },
    {
      "id": "R9JPPPP5",
      "riskyWindow": {
        "from": "2021-07-24T00:00:00Z",
        "until": "2021-07-24T22:59:00Z"
      },
      "messageType": "M2"
    },
    {
      "id": "5XXM3M85",
      "riskyWindow": {
        "from": "2021-07-24T00:00:00Z",
        "until": "2021-07-24T22:59:00Z"
      },
      "messageType": "M2"
    },
    {
      "id": "RPM9M2X5",
      "riskyWindow": {
        "from": "2021-07-24T00:00:00Z",
        "until": "2021-07-24T22:59:00Z"
      },
      "messageType": "M2"
    },
    {
      "id": "5Y3V33W5",
      "riskyWindow": {
        "from": "2021-07-24T00:00:00Z",
        "until": "2021-07-24T22:59:00Z"
      },
      "messageType": "M2"
    },
    {
      "id": "R9J9JJV2",
      "riskyWindow": {
        "from": "2021-07-26T00:00:00Z",
        "until": "2021-07-26T22:59:00Z"
      },
      "messageType": "M2"
    },
    {
      "id": "52WJP89R",
      "riskyWindow": {
        "from": "2021-07-25T23:00:00Z",
        "until": "2021-07-26T22:59:59Z"
      },
      "messageType": "M2"
    },
    {
      "id": "5Y69VVXR",
      "riskyWindow": {
        "from": "2021-07-24T00:00:00Z",
        "until": "2021-07-24T22:59:00Z"
      },
      "messageType": "M2"
    },
    {
      "id": "5WVMYY4P",
      "riskyWindow": {
        "from": "2021-07-25T00:00:00Z",
        "until": "2021-07-25T22:59:00Z"
      },
      "messageType": "M2"
    },
    {
      "id": "5VK3VY9R",
      "riskyWindow": {
        "from": "2021-07-25T00:00:00Z",
        "until": "2021-07-25T22:59:00Z"
      },
      "messageType": "M2"
    }
  ]
}
