{
  "venues": [
    {
      "id": "53W63382",
      "riskyWindow": {
        "from": "2021-12-07T00:00:00Z",
        "until": "2021-12-07T23:59:59Z"
      },
      "messageType": "M2"
    },
    {
      "id": "RP68X32R",
      "riskyWindow": {
        "from": "2021-12-08T00:00:00Z",
        "until": "2021-12-08T23:59:59Z"
      },
      "messageType": "M2"
    },
    {
      "id": "5W4WVWPR",
      "riskyWindow": {
        "from": "2021-12-09T00:00:00Z",
        "until": "2021-12-09T23:59:59Z"
      },
      "messageType": "M2"
    },
    {
      "id": "5YYXVVY5",
      "riskyWindow": {
        "from": "2021-12-08T00:00:00Z",
        "until": "2021-12-08T23:59:59Z"
      },
      "messageType": "M2"
    },
    {
      "id": "5YXVVPPR",
      "riskyWindow": {
        "from": "2021-12-08T00:00:00Z",
        "until": "2021-12-08T23:59:59Z"
      },
      "messageType": "M2"
    },
    {
      "id": "53MX8665",
      "riskyWindow": {
        "from": "2021-12-07T00:00:00Z",
        "until": "2021-12-07T23:59:59Z"
      },
      "messageType": "M2"
    },
    {
      "id": "52WV364R",
      "riskyWindow": {
        "from": "2021-12-08T00:00:00Z",
        "until": "2021-12-08T23:59:59Z"
      },
      "messageType": "M2"
    },
    {
      "id": "548J43V5",
      "riskyWindow": {
        "from": "2021-12-08T00:00:00Z",
        "until": "2021-12-08T23:59:59Z"
      },
      "messageType": "M2"
    },
    {
      "id": "RP92J84J",
      "riskyWindow": {
        "from": "2021-12-08T00:00:00Z",
        "until": "2021-12-08T23:59:59Z"
      },
      "messageType": "M2"
    },
    {
      "id": "5VK3YK4R",
      "riskyWindow": {
        "from": "2021-12-07T00:00:00Z",
        "until": "2021-12-07T23:59:59Z"
      },
      "messageType": "M2"
    },
    {
      "id": "5M44Y4YR",
      "riskyWindow": {
        "from": "2021-12-07T00:00:00Z",
        "until": "2021-12-07T23:59:59Z"
      },
      "messageType": "M2"
    },
    {
      "id": "R82MMVMR",
      "riskyWindow": {
        "from": "2021-12-07T00:00:00Z",
        "until": "2021-12-07T23:59:59Z"
      },
      "messageType": "M2"
    },
    {
      "id": "5Y9Y83MW",
      "riskyWindow": {
        "from": "2021-12-08T00:00:00Z",
        "until": "2021-12-08T23:59:59Z"
      },
      "messageType": "M2"
    },
    {
      "id": "RK626635",
      "riskyWindow": {
        "from": "2021-12-07T00:00:00Z",
        "until": "2021-12-07T23:59:59Z"
      },
      "messageType": "M2"
    },
    {
      "id": "5Y69JMWR",
      "riskyWindow": {
        "from": "2021-12-07T00:00:00Z",
        "until": "2021-12-07T23:59:59Z"
      },
      "messageType": "M2"
    },
    {
      "id": "5VXJ82K5",
      "riskyWindow": {
        "from": "2021-12-07T00:00:00Z",
        "until": "2021-12-07T23:59:59Z"
      },
      "messageType": "M2"
    },
    {
      "id": "5W323YJ5",
      "riskyWindow": {
        "from": "2021-12-07T00:00:00Z",
        "until": "2021-12-07T23:59:59Z"
      },
      "messageType": "M2"
    },
    {
      "id": "52XK3385",
      "riskyWindow": {
        "from": "2021-12-07T00:00:00Z",
        "until": "2021-12-07T23:59:59Z"
      },
      "messageType": "M2"
    },
    {
      "id": "R9PPPY25",
      "riskyWindow": {
        "from": "2021-12-07T00:00:00Z",
        "until": "2021-12-07T23:59:59Z"
      },
      "messageType": "M2"
    },
    {
      "id": "5MWK283W",
      "riskyWindow": {
        "from": "2021-12-08T00:00:00Z",
        "until": "2021-12-08T23:59:59Z"
      },
      "messageType": "M2"
    },
    {
      "id": "RK32VK3R",
      "riskyWindow": {
        "from": "2021-12-07T00:00:00Z",
        "until": "2021-12-07T23:59:59Z"
      },
      "messageType": "M2"
    },
    {
      "id": "R9JKJYVX",
      "riskyWindow": {
        "from": "2021-12-05T00:00:00Z",
        "until": "2021-12-05T23:59:00Z"
      },
      "messageType": "M2"
    },
    {
      "id": "534Y22JR",
      "riskyWindow": {
        "from": "2021-12-05T00:00:00Z",
        "until": "2021-12-05T23:59:00Z"
      },
      "messageType": "M2"
    },
    {
      "id": "5XX6WJK5",
      "riskyWindow": {
        "from": "2021-12-05T00:00:00Z",
        "until": "2021-12-05T23:59:00Z"
      },
      "messageType": "M2"
    },
    {
      "id": "R8V82898",
      "riskyWindow": {
        "from": "2021-12-05T00:00:00Z",
        "until": "2021-12-05T23:59:00Z"
      },
      "messageType": "M2"
    },
    {
      "id": "RK88XWK5",
      "riskyWindow": {
        "from": "2021-12-07T00:00:00Z",
        "until": "2021-12-07T23:59:00Z"
      },
      "messageType": "M2"
    },
    {
      "id": "5VX642P5",
      "riskyWindow": {
        "from": "2021-12-06T00:00:00Z",
        "until": "2021-12-06T23:59:00Z"
      },
      "messageType": "M2"
    },
    {
      "id": "5WV6YXWP",
      "riskyWindow": {
        "from": "2021-12-06T12:00:00Z",
        "until": "2021-12-06T23:59:00Z"
      },
      "messageType": "M2"
    },
    {
      "id": "R9JJM83X",
      "riskyWindow": {
        "from": "2021-12-05T00:00:00Z",
        "until": "2021-12-05T23:59:00Z"
      },
      "messageType": "M2"
    },
    {
      "id": "RK39966R",
      "riskyWindow": {
        "from": "2021-12-05T12:00:00Z",
        "until": "2021-12-05T23:59:00Z"
      },
      "messageType": "M2"
    },
    {
      "id": "RK6PJ625",
      "riskyWindow": {
        "from": "2021-12-06T12:00:00Z",
        "until": "2021-12-06T23:59:00Z"
      },
      "messageType": "M2"
    },
    {
      "id": "542WP2VP",
      "riskyWindow": {
        "from": "2021-12-05T00:00:00Z",
        "until": "2021-12-05T23:59:00Z"
      },
      "messageType": "M2"
    },
    {
      "id": "5YYX6X95",
      "riskyWindow": {
        "from": "2021-12-05T00:00:00Z",
        "until": "2021-12-05T23:59:00Z"
      },
      "messageType": "M2"
    },
    {
      "id": "53VXY42R",
      "riskyWindow": {
        "from": "2021-12-05T00:00:00Z",
        "until": "2021-12-05T23:59:00Z"
      },
      "messageType": "M2"
    },
    {
      "id": "P562JWY5",
      "riskyWindow": {
        "from": "2021-12-06T00:00:00Z",
        "until": "2021-12-06T23:59:00Z"
      },
      "messageType": "M2"
    },
    {
      "id": "53WKPWY5",
      "riskyWindow": {
        "from": "2021-12-05T00:00:00Z",
        "until": "2021-12-05T23:59:00Z"
      },
      "messageType": "M2"
    },
    {
      "id": "RPYW62X5",
      "riskyWindow": {
        "from": "2021-12-05T00:00:00Z",
        "until": "2021-12-05T23:59:00Z"
      },
      "messageType": "M2"
    },
    {
      "id": "5YVW44PR",
      "riskyWindow": {
        "from": "2021-12-05T00:00:00Z",
        "until": "2021-12-05T23:59:00Z"
      },
      "messageType": "M2"
    },
    {
      "id": "566P4P35",
      "riskyWindow": {
        "from": "2021-12-06T00:00:00Z",
        "until": "2021-12-06T23:59:00Z"
      },
      "messageType": "M2"
    },
    {
      "id": "M53Y24Y5",
      "riskyWindow": {
        "from": "2021-12-05T12:00:00Z",
        "until": "2021-12-05T23:59:00Z"
      },
      "messageType": "M2"
    },
    {
      "id": "5VVWK245",
      "riskyWindow": {
        "from": "2021-12-05T00:00:00Z",
        "until": "2021-12-05T23:59:00Z"
      },
      "messageType": "M2"
    },
    {
      "id": "5XY24MYR",
      "riskyWindow": {
        "from": "2021-12-05T12:00:00Z",
        "until": "2021-12-05T23:59:00Z"
      },
      "messageType": "M2"
    },
    {
      "id": "5WV6YJ9P",
      "riskyWindow": {
        "from": "2021-12-05T00:00:00Z",
        "until": "2021-12-05T23:59:00Z"
      },
      "messageType": "M2"
    },
    {
      "id": "5YY2PJ85",
      "riskyWindow": {
        "from": "2021-12-08T12:00:00Z",
        "until": "2021-12-08T23:59:00Z"
      },
      "messageType": "M2"
    },
    {
      "id": "RP98K3YK",
      "riskyWindow": {
        "from": "2021-12-05T00:00:00Z",
        "until": "2021-12-05T23:59:00Z"
      },
      "messageType": "M2"
    },
    {
      "id": "RJX2M6MR",
      "riskyWindow": {
        "from": "2021-12-06T12:00:00Z",
        "until": "2021-12-06T23:59:00Z"
      },
      "messageType": "M2"
    },
    {
      "id": "X5Y6Y9YR",
      "riskyWindow": {
        "from": "2021-12-05T12:00:00Z",
        "until": "2021-12-05T23:59:00Z"
      },
      "messageType": "M2"
    },
    {
      "id": "56KKK33R",
      "riskyWindow": {
        "from": "2021-12-05T12:00:00Z",
        "until": "2021-12-05T23:59:00Z"
      },
      "messageType": "M2"
    },
    {
      "id": "5WVXPKVR",
      "riskyWindow": {
        "from": "2021-12-08T12:00:00Z",
        "until": "2021-12-08T23:59:00Z"
      },
      "messageType": "M2"
    },
    {
      "id": "RPW43KK5",
      "riskyWindow": {
        "from": "2021-12-05T12:00:00Z",
        "until": "2021-12-05T23:59:00Z"
      },
      "messageType": "M2"
    },
    {
      "id": "RJV8224M",
      "riskyWindow": {
        "from": "2021-12-05T12:00:00Z",
        "until": "2021-12-05T23:59:00Z"
      },
      "messageType": "M2"
    },
    {
      "id": "RKYPJ68R",
      "riskyWindow": {
        "from": "2021-12-05T12:00:00Z",
        "until": "2021-12-05T23:59:00Z"
      },
      "messageType": "M2"
    },
    {
      "id": "RP9P36KV",
      "riskyWindow": {
        "from": "2021-12-05T00:00:00Z",
        "until": "2021-12-05T23:59:00Z"
      },
      "messageType": "M2"
    },
    {
      "id": "52VMYM95",
      "riskyWindow": {
        "from": "2021-12-05T12:00:00Z",
        "until": "2021-12-05T23:59:00Z"
      },
      "messageType": "M2"
    },
    {
      "id": "53W2VP44",
      "riskyWindow": {
        "from": "2021-12-06T12:00:00Z",
        "until": "2021-12-06T23:59:00Z"
      },
      "messageType": "M2"
    },
    {
      "id": "5W8MPKJR",
      "riskyWindow": {
        "from": "2021-12-06T12:00:00Z",
        "until": "2021-12-06T23:59:00Z"
      },
      "messageType": "M2"
    },
    {
      "id": "53WJ4KKJ",
      "riskyWindow": {
        "from": "2021-12-05T12:00:00Z",
        "until": "2021-12-05T23:59:00Z"
      },
      "messageType": "M2"
    },
    {
      "id": "5MW992Y5",
      "riskyWindow": {
        "from": "2021-12-05T00:00:00Z",
        "until": "2021-12-05T23:59:00Z"
      },
      "messageType": "M2"
    },
    {
      "id": "5M8J628R",
      "riskyWindow": {
        "from": "2021-12-05T00:00:00Z",
        "until": "2021-12-05T23:59:00Z"
      },
      "messageType": "M2"
    },
    {
      "id": "5X82PYK5",
      "riskyWindow": {
        "from": "2021-12-05T12:00:00Z",
        "until": "2021-12-05T23:59:00Z"
      },
      "messageType": "M2"
    },
    {
      "id": "R84PYW8R",
      "riskyWindow": {
        "from": "2021-12-05T12:00:00Z",
        "until": "2021-12-05T23:59:00Z"
      },
      "messageType": "M2"
    },
    {
      "id": "54866JP5",
      "riskyWindow": {
        "from": "2021-12-05T12:00:00Z",
        "until": "2021-12-05T23:59:00Z"
      },
      "messageType": "M2"
    },
    {
      "id": "5V62J385",
      "riskyWindow": {
        "from": "2021-12-05T12:00:00Z",
        "until": "2021-12-05T23:59:00Z"
      },
      "messageType": "M2"
    },
    {
      "id": "549Y8P4R",
      "riskyWindow": {
        "from": "2021-12-05T12:00:00Z",
        "until": "2021-12-05T23:59:00Z"
      },
      "messageType": "M2"
    },
    {
      "id": "542MX9VP",
      "riskyWindow": {
        "from": "2021-12-05T00:00:00Z",
        "until": "2021-12-05T23:59:00Z"
      },
      "messageType": "M2"
    },
    {
      "id": "5XX6K4W5",
      "riskyWindow": {
        "from": "2021-12-05T12:00:00Z",
        "until": "2021-12-05T23:59:00Z"
      },
      "messageType": "M2"
    },
    {
      "id": "R8VP4628",
      "riskyWindow": {
        "from": "2021-12-05T12:00:00Z",
        "until": "2021-12-05T23:59:00Z"
      },
      "messageType": "M2"
    },
    {
      "id": "RP68X32R",
      "riskyWindow": {
        "from": "2021-12-05T00:00:00Z",
        "until": "2021-12-05T23:59:00Z"
      },
      "messageType": "M2"
    },
    {
      "id": "R9J6WXXV",
      "riskyWindow": {
        "from": "2021-12-05T00:00:00Z",
        "until": "2021-12-05T23:59:00Z"
      },
      "messageType": "M2"
    },
    {
      "id": "5VWPWM8R",
      "riskyWindow": {
        "from": "2021-12-05T12:00:00Z",
        "until": "2021-12-05T23:59:00Z"
      },
      "messageType": "M2"
    },
    {
      "id": "52W3PPXR",
      "riskyWindow": {
        "from": "2021-12-05T12:00:00Z",
        "until": "2021-12-05T23:59:00Z"
      },
      "messageType": "M2"
    },
    {
      "id": "RP289WJR",
      "riskyWindow": {
        "from": "2021-12-05T12:00:00Z",
        "until": "2021-12-05T23:59:00Z"
      },
      "messageType": "M2"
    },
    {
      "id": "R9JYXJYV",
      "riskyWindow": {
        "from": "2021-12-05T00:00:00Z",
        "until": "2021-12-05T23:59:00Z"
      },
      "messageType": "M2"
    },
    {
      "id": "RJVK6WVR",
      "riskyWindow": {
        "from": "2021-12-05T12:00:00Z",
        "until": "2021-12-05T23:59:00Z"
      },
      "messageType": "M2"
    },
    {
      "id": "54MP96YR",
      "riskyWindow": {
        "from": "2021-12-05T12:00:00Z",
        "until": "2021-12-05T23:59:00Z"
      },
      "messageType": "M2"
    },
    {
      "id": "5W83YW8R",
      "riskyWindow": {
        "from": "2021-12-05T12:00:00Z",
        "until": "2021-12-05T23:59:00Z"
      },
      "messageType": "M2"
    },
    {
      "id": "53V983VR",
      "riskyWindow": {
        "from": "2021-12-05T12:00:00Z",
        "until": "2021-12-05T23:59:00Z"
      },
      "messageType": "M2"
    },
    {
      "id": "5Y934W8W",
      "riskyWindow": {
        "from": "2021-12-05T12:00:00Z",
        "until": "2021-12-05T23:59:00Z"
      },
      "messageType": "M2"
    },
    {
      "id": "5M69XM8R",
      "riskyWindow": {
        "from": "2021-12-05T12:00:00Z",
        "until": "2021-12-05T23:59:00Z"
      },
      "messageType": "M2"
    },
    {
      "id": "R8V828W8",
      "riskyWindow": {
        "from": "2021-12-06T00:00:00Z",
        "until": "2021-12-06T23:59:00Z"
      },
      "messageType": "M2"
    },
    {
      "id": "RJV43MWR",
      "riskyWindow": {
        "from": "2021-12-05T12:00:00Z",
        "until": "2021-12-05T23:59:00Z"
      },
      "messageType": "M2"
    },
    {
      "id": "RJ2VJ82R",
      "riskyWindow": {
        "from": "2021-12-05T12:00:00Z",
        "until": "2021-12-05T23:59:00Z"
      },
      "messageType": "M2"
    },
    {
      "id": "RPVP2X9R",
      "riskyWindow": {
        "from": "2021-12-05T12:00:00Z",
        "until": "2021-12-05T23:59:00Z"
      },
      "messageType": "M2"
    },
    {
      "id": "5Y9Y2PKP",
      "riskyWindow": {
        "from": "2021-12-05T00:00:00Z",
        "until": "2021-12-05T23:59:00Z"
      },
      "messageType": "M2"
    },
    {
      "id": "X5YYP2P5",
      "riskyWindow": {
        "from": "2021-12-05T00:00:00Z",
        "until": "2021-12-05T23:59:00Z"
      },
      "messageType": "M2"
    },
    {
      "id": "RKJV2885",
      "riskyWindow": {
        "from": "2021-12-05T12:00:00Z",
        "until": "2021-12-05T23:59:00Z"
      },
      "messageType": "M2"
    },
    {
      "id": "5X88MW45",
      "riskyWindow": {
        "from": "2021-12-05T12:00:00Z",
        "until": "2021-12-05T23:59:00Z"
      },
      "messageType": "M2"
    },
    {
      "id": "5W3K63W5",
      "riskyWindow": {
        "from": "2021-12-05T12:00:00Z",
        "until": "2021-12-05T23:59:00Z"
      },
      "messageType": "M2"
    },
    {
      "id": "526P4KK5",
      "riskyWindow": {
        "from": "2021-12-05T00:00:00Z",
        "until": "2021-12-05T23:59:00Z"
      },
      "messageType": "M2"
    },
    {
      "id": "5XXY34K5",
      "riskyWindow": {
        "from": "2021-12-05T00:00:00Z",
        "until": "2021-12-05T23:59:00Z"
      },
      "messageType": "M2"
    },
    {
      "id": "5426P44Y",
      "riskyWindow": {
        "from": "2021-12-08T12:00:00Z",
        "until": "2021-12-08T23:59:00Z"
      },
      "messageType": "M2"
    },
    {
      "id": "RJV6J44M",
      "riskyWindow": {
        "from": "2021-12-05T12:00:00Z",
        "until": "2021-12-05T23:59:00Z"
      },
      "messageType": "M2"
    },
    {
      "id": "5WVYVYKX",
      "riskyWindow": {
        "from": "2021-12-05T00:00:00Z",
        "until": "2021-12-05T23:59:00Z"
      },
      "messageType": "M2"
    },
    {
      "id": "52KV269R",
      "riskyWindow": {
        "from": "2021-12-05T12:00:00Z",
        "until": "2021-12-05T23:59:00Z"
      },
      "messageType": "M2"
    },
    {
      "id": "RP4W33KR",
      "riskyWindow": {
        "from": "2021-12-05T12:00:00Z",
        "until": "2021-12-05T23:59:00Z"
      },
      "messageType": "M2"
    },
    {
      "id": "5VPJMKY5",
      "riskyWindow": {
        "from": "2021-12-05T12:00:00Z",
        "until": "2021-12-05T23:59:00Z"
      },
      "messageType": "M2"
    },
    {
      "id": "KR9W9WVR",
      "riskyWindow": {
        "from": "2021-12-06T12:00:00Z",
        "until": "2021-12-06T23:59:00Z"
      },
      "messageType": "M2"
    },
    {
      "id": "5V663Y45",
      "riskyWindow": {
        "from": "2021-12-07T12:00:00Z",
        "until": "2021-12-07T23:59:00Z"
      },
      "messageType": "M2"
    },
    {
      "id": "5428XMK3",
      "riskyWindow": {
        "from": "2021-12-05T00:00:00Z",
        "until": "2021-12-05T23:59:00Z"
      },
      "messageType": "M2"
    },
    {
      "id": "RPJ6KJKR",
      "riskyWindow": {
        "from": "2021-12-06T00:00:00Z",
        "until": "2021-12-06T23:59:00Z"
      },
      "messageType": "M2"
    },
    {
      "id": "RK8K8825",
      "riskyWindow": {
        "from": "2021-12-05T00:00:00Z",
        "until": "2021-12-05T23:59:00Z"
      },
      "messageType": "M2"
    },
    {
      "id": "5WV33WJV",
      "riskyWindow": {
        "from": "2021-12-05T00:00:00Z",
        "until": "2021-12-05T23:59:00Z"
      },
      "messageType": "M2"
    },
    {
      "id": "RJVPV4Y9",
      "riskyWindow": {
        "from": "2021-12-05T12:00:00Z",
        "until": "2021-12-05T23:59:00Z"
      },
      "messageType": "M2"
    },
    {
      "id": "RPY89395",
      "riskyWindow": {
        "from": "2021-12-05T00:00:00Z",
        "until": "2021-12-05T23:59:00Z"
      },
      "messageType": "M2"
    },
    {
      "id": "5YY22JP5",
      "riskyWindow": {
        "from": "2021-12-05T12:00:00Z",
        "until": "2021-12-05T23:59:00Z"
      },
      "messageType": "M2"
    },
    {
      "id": "V5VX64Y5",
      "riskyWindow": {
        "from": "2021-12-05T12:00:00Z",
        "until": "2021-12-05T23:59:00Z"
      },
      "messageType": "M2"
    },
    {
      "id": "RJW6YY95",
      "riskyWindow": {
        "from": "2021-12-05T00:00:00Z",
        "until": "2021-12-05T23:59:00Z"
      },
      "messageType": "M2"
    },
    {
      "id": "R98V4X25",
      "riskyWindow": {
        "from": "2021-12-05T00:00:00Z",
        "until": "2021-12-05T23:59:00Z"
      },
      "messageType": "M2"
    },
    {
      "id": "5VJWKJ95",
      "riskyWindow": {
        "from": "2021-12-05T12:00:00Z",
        "until": "2021-12-05T23:59:00Z"
      },
      "messageType": "M2"
    },
    {
      "id": "R999VYXR",
      "riskyWindow": {
        "from": "2021-12-05T12:00:00Z",
        "until": "2021-12-05T23:59:00Z"
      },
      "messageType": "M2"
    },
    {
      "id": "R8K2K2M5",
      "riskyWindow": {
        "from": "2021-12-05T12:00:00Z",
        "until": "2021-12-05T23:59:00Z"
      },
      "messageType": "M2"
    },
    {
      "id": "5VWWM2YR",
      "riskyWindow": {
        "from": "2021-12-05T00:00:00Z",
        "until": "2021-12-05T23:59:00Z"
      },
      "messageType": "M2"
    },
    {
      "id": "56JK3W45",
      "riskyWindow": {
        "from": "2021-12-05T00:00:00Z",
        "until": "2021-12-05T23:59:00Z"
      },
      "messageType": "M2"
    },
    {
      "id": "R8298PVR",
      "riskyWindow": {
        "from": "2021-12-05T00:00:00Z",
        "until": "2021-12-05T23:59:00Z"
      },
      "messageType": "M2"
    },
    {
      "id": "RPY26YJ5",
      "riskyWindow": {
        "from": "2021-12-06T12:00:00Z",
        "until": "2021-12-06T23:59:00Z"
      },
      "messageType": "M2"
    },
    {
      "id": "5MW82PX5",
      "riskyWindow": {
        "from": "2021-12-05T12:00:00Z",
        "until": "2021-12-05T23:59:00Z"
      },
      "messageType": "M2"
    },
    {
      "id": "52868PP5",
      "riskyWindow": {
        "from": "2021-12-05T00:00:00Z",
        "until": "2021-12-05T23:59:00Z"
      },
      "messageType": "M2"
    },
    {
      "id": "5MMJ4485",
      "riskyWindow": {
        "from": "2021-12-05T00:00:00Z",
        "until": "2021-12-05T23:59:00Z"
      },
      "messageType": "M2"
    },
    {
      "id": "R8232W8R",
      "riskyWindow": {
        "from": "2021-12-05T00:00:00Z",
        "until": "2021-12-05T23:59:00Z"
      },
      "messageType": "M2"
    },
    {
      "id": "RJ9XMY85",
      "riskyWindow": {
        "from": "2021-12-05T00:00:00Z",
        "until": "2021-12-05T23:59:00Z"
      },
      "messageType": "M2"
    },
    {
      "id": "568XW9PJ",
      "riskyWindow": {
        "from": "2021-12-05T12:00:00Z",
        "until": "2021-12-05T23:59:00Z"
      },
      "messageType": "M2"
    },
    {
      "id": "5VK2J4KR",
      "riskyWindow": {
        "from": "2021-12-05T00:00:00Z",
        "until": "2021-12-05T23:59:00Z"
      },
      "messageType": "M2"
    },
    {
      "id": "R9M6829R",
      "riskyWindow": {
        "from": "2021-12-05T12:00:00Z",
        "until": "2021-12-05T23:59:00Z"
      },
      "messageType": "M2"
    },
    {
      "id": "5286J845",
      "riskyWindow": {
        "from": "2021-12-05T12:00:00Z",
        "until": "2021-12-05T23:59:00Z"
      },
      "messageType": "M2"
    },
    {
      "id": "526MPPP5",
      "riskyWindow": {
        "from": "2021-12-05T12:00:00Z",
        "until": "2021-12-05T23:59:00Z"
      },
      "messageType": "M2"
    },
    {
      "id": "R9PY44Y5",
      "riskyWindow": {
        "from": "2021-12-05T12:00:00Z",
        "until": "2021-12-05T23:59:00Z"
      },
      "messageType": "M2"
    },
    {
      "id": "52WJ9MJ9",
      "riskyWindow": {
        "from": "2021-12-06T00:00:00Z",
        "until": "2021-12-06T23:59:00Z"
      },
      "messageType": "M2"
    },
    {
      "id": "5W648WMR",
      "riskyWindow": {
        "from": "2021-12-05T00:00:00Z",
        "until": "2021-12-05T23:59:00Z"
      },
      "messageType": "M2"
    },
    {
      "id": "RJV6944W",
      "riskyWindow": {
        "from": "2021-12-05T12:00:00Z",
        "until": "2021-12-05T23:59:00Z"
      },
      "messageType": "M2"
    },
    {
      "id": "RJVV929R",
      "riskyWindow": {
        "from": "2021-12-05T00:00:00Z",
        "until": "2021-12-05T23:59:00Z"
      },
      "messageType": "M2"
    },
    {
      "id": "568XKK45",
      "riskyWindow": {
        "from": "2021-12-05T00:00:00Z",
        "until": "2021-12-05T23:59:00Z"
      },
      "messageType": "M2"
    },
    {
      "id": "53J3P8YR",
      "riskyWindow": {
        "from": "2021-12-06T00:00:00Z",
        "until": "2021-12-06T23:59:00Z"
      },
      "messageType": "M2"
    }
  ]
}
