{
  "venues": [
    {
      "id": "5V6Y9P45",
      "riskyWindow": {
        "from": "2021-07-03T00:00:00Z",
        "until": "2021-07-03T22:59:00Z"
      },
      "messageType": "M2"
    },
    {
      "id": "RK34K33R",
      "riskyWindow": {
        "from": "2021-07-04T00:00:00Z",
        "until": "2021-07-04T22:59:00Z"
      },
      "messageType": "M2"
    },
    {
      "id": "5XVPJY45",
      "riskyWindow": {
        "from": "2021-07-03T00:00:00Z",
        "until": "2021-07-03T22:59:00Z"
      },
      "messageType": "M2"
    },
    {
      "id": "5XMYW34R",
      "riskyWindow": {
        "from": "2021-07-02T00:00:00Z",
        "until": "2021-07-02T22:59:00Z"
      },
      "messageType": "M2"
    },
    {
      "id": "RJV3YP8R",
      "riskyWindow": {
        "from": "2021-07-03T00:00:00Z",
        "until": "2021-07-03T22:59:00Z"
      },
      "messageType": "M2"
    },
    {
      "id": "R864YKKR",
      "riskyWindow": {
        "from": "2021-07-03T00:00:00Z",
        "until": "2021-07-03T22:59:00Z"
      },
      "messageType": "M2"
    },
    {
      "id": "5X2JX3K5",
      "riskyWindow": {
        "from": "2021-07-03T00:00:00Z",
        "until": "2021-07-03T22:59:00Z"
      },
      "messageType": "M2"
    },
    {
      "id": "RKYVYJ8R",
      "riskyWindow": {
        "from": "2021-07-03T00:00:00Z",
        "until": "2021-07-03T22:59:00Z"
      },
      "messageType": "M2"
    },
    {
      "id": "RK933Y4R",
      "riskyWindow": {
        "from": "2021-07-05T00:00:00Z",
        "until": "2021-07-05T22:59:00Z"
      },
      "messageType": "M2"
    },
    {
      "id": "MR89XM25",
      "riskyWindow": {
        "from": "2021-07-03T00:00:00Z",
        "until": "2021-07-03T22:59:00Z"
      },
      "messageType": "M2"
    },
    {
      "id": "5MVXXPYR",
      "riskyWindow": {
        "from": "2021-07-04T00:00:00Z",
        "until": "2021-07-04T22:59:00Z"
      },
      "messageType": "M2"
    },
    {
      "id": "RK8PP335",
      "riskyWindow": {
        "from": "2021-07-03T00:00:00Z",
        "until": "2021-07-03T22:59:00Z"
      },
      "messageType": "M2"
    },
    {
      "id": "R99VMKVR",
      "riskyWindow": {
        "from": "2021-07-04T00:00:00Z",
        "until": "2021-07-04T22:59:00Z"
      },
      "messageType": "M2"
    },
    {
      "id": "52W36X8K",
      "riskyWindow": {
        "from": "2021-07-04T00:00:00Z",
        "until": "2021-07-04T22:59:00Z"
      },
      "messageType": "M2"
    },
    {
      "id": "53YY2X25",
      "riskyWindow": {
        "from": "2021-07-04T00:00:00Z",
        "until": "2021-07-04T22:59:00Z"
      },
      "messageType": "M2"
    },
    {
      "id": "5692W23R",
      "riskyWindow": {
        "from": "2021-07-05T00:00:00Z",
        "until": "2021-07-05T22:59:00Z"
      },
      "messageType": "M2"
    },
    {
      "id": "R86M3Y6R",
      "riskyWindow": {
        "from": "2021-07-03T00:00:00Z",
        "until": "2021-07-03T22:59:00Z"
      },
      "messageType": "M2"
    },
    {
      "id": "56928YMR",
      "riskyWindow": {
        "from": "2021-07-04T00:00:00Z",
        "until": "2021-07-04T22:59:00Z"
      },
      "messageType": "M2"
    },
    {
      "id": "533PXVW5",
      "riskyWindow": {
        "from": "2021-07-04T00:00:00Z",
        "until": "2021-07-04T22:59:00Z"
      },
      "messageType": "M2"
    },
    {
      "id": "53WV6YY6",
      "riskyWindow": {
        "from": "2021-07-03T00:00:00Z",
        "until": "2021-07-03T22:59:00Z"
      },
      "messageType": "M2"
    },
    {
      "id": "R96XXV95",
      "riskyWindow": {
        "from": "2021-07-03T00:00:00Z",
        "until": "2021-07-03T22:59:00Z"
      },
      "messageType": "M2"
    },
    {
      "id": "RP44K3VR",
      "riskyWindow": {
        "from": "2021-07-03T00:00:00Z",
        "until": "2021-07-03T22:59:00Z"
      },
      "messageType": "M2"
    },
    {
      "id": "542WP335",
      "riskyWindow": {
        "from": "2021-07-04T00:00:00Z",
        "until": "2021-07-04T22:59:00Z"
      },
      "messageType": "M2"
    },
    {
      "id": "RJVK6JWR",
      "riskyWindow": {
        "from": "2021-07-03T00:00:00Z",
        "until": "2021-07-03T22:59:00Z"
      },
      "messageType": "M2"
    },
    {
      "id": "56YJWWJR",
      "riskyWindow": {
        "from": "2021-07-03T00:00:00Z",
        "until": "2021-07-03T22:59:00Z"
      },
      "messageType": "M2"
    },
    {
      "id": "52K3WW4R",
      "riskyWindow": {
        "from": "2021-07-04T00:00:00Z",
        "until": "2021-07-04T22:59:00Z"
      },
      "messageType": "M2"
    },
    {
      "id": "RK3WY46R",
      "riskyWindow": {
        "from": "2021-07-05T00:00:00Z",
        "until": "2021-07-05T22:59:00Z"
      },
      "messageType": "M2"
    },
    {
      "id": "5XV6PXY5",
      "riskyWindow": {
        "from": "2021-07-04T00:00:00Z",
        "until": "2021-07-04T22:59:00Z"
      },
      "messageType": "M2"
    },
    {
      "id": "RKYX8KW8",
      "riskyWindow": {
        "from": "2021-07-03T00:00:00Z",
        "until": "2021-07-03T22:59:00Z"
      },
      "messageType": "M2"
    },
    {
      "id": "RJ22PM6R",
      "riskyWindow": {
        "from": "2021-07-03T00:00:00Z",
        "until": "2021-07-03T22:59:00Z"
      },
      "messageType": "M2"
    },
    {
      "id": "52WP96KK",
      "riskyWindow": {
        "from": "2021-07-03T00:00:00Z",
        "until": "2021-07-03T22:59:00Z"
      },
      "messageType": "M2"
    },
    {
      "id": "RKYWVY8R",
      "riskyWindow": {
        "from": "2021-07-04T00:00:00Z",
        "until": "2021-07-04T22:59:00Z"
      },
      "messageType": "M2"
    },
    {
      "id": "5X8YXPW5",
      "riskyWindow": {
        "from": "2021-07-05T00:00:00Z",
        "until": "2021-07-05T22:59:00Z"
      },
      "messageType": "M2"
    },
    {
      "id": "5WX38WJR",
      "riskyWindow": {
        "from": "2021-07-03T00:00:00Z",
        "until": "2021-07-03T22:59:00Z"
      },
      "messageType": "M2"
    },
    {
      "id": "5XK32W3R",
      "riskyWindow": {
        "from": "2021-07-03T00:00:00Z",
        "until": "2021-07-03T22:59:00Z"
      },
      "messageType": "M2"
    },
    {
      "id": "5XYVP84R",
      "riskyWindow": {
        "from": "2021-07-03T00:00:00Z",
        "until": "2021-07-03T22:59:00Z"
      },
      "messageType": "M2"
    },
    {
      "id": "R9MKYP2R",
      "riskyWindow": {
        "from": "2021-07-03T00:00:00Z",
        "until": "2021-07-03T22:59:00Z"
      },
      "messageType": "M2"
    },
    {
      "id": "5466M2M5",
      "riskyWindow": {
        "from": "2021-07-03T00:00:00Z",
        "until": "2021-07-03T22:59:00Z"
      },
      "messageType": "M2"
    },
    {
      "id": "52W2W2J9",
      "riskyWindow": {
        "from": "2021-07-03T00:00:00Z",
        "until": "2021-07-03T22:59:00Z"
      },
      "messageType": "M2"
    },
    {
      "id": "5W9999W5",
      "riskyWindow": {
        "from": "2021-07-03T00:00:00Z",
        "until": "2021-07-03T22:59:00Z"
      },
      "messageType": "M2"
    },
    {
      "id": "4RJ3V985",
      "riskyWindow": {
        "from": "2021-07-05T00:00:00Z",
        "until": "2021-07-05T22:59:00Z"
      },
      "messageType": "M2"
    },
    {
      "id": "53WJVV4V",
      "riskyWindow": {
        "from": "2021-07-04T00:00:00Z",
        "until": "2021-07-04T22:59:00Z"
      },
      "messageType": "M2"
    },
    {
      "id": "RP8VXXJR",
      "riskyWindow": {
        "from": "2021-07-03T00:00:00Z",
        "until": "2021-07-03T22:59:00Z"
      },
      "messageType": "M2"
    },
    {
      "id": "RJ6J9V2R",
      "riskyWindow": {
        "from": "2021-07-04T00:00:00Z",
        "until": "2021-07-04T22:59:00Z"
      },
      "messageType": "M2"
    },
    {
      "id": "R8KV9P85",
      "riskyWindow": {
        "from": "2021-07-03T00:00:00Z",
        "until": "2021-07-03T22:59:00Z"
      },
      "messageType": "M2"
    },
    {
      "id": "5Y9Y84P5",
      "riskyWindow": {
        "from": "2021-07-03T00:00:00Z",
        "until": "2021-07-03T22:59:00Z"
      },
      "messageType": "M2"
    },
    {
      "id": "542MP98M",
      "riskyWindow": {
        "from": "2021-07-03T00:00:00Z",
        "until": "2021-07-03T22:59:00Z"
      },
      "messageType": "M2"
    },
    {
      "id": "5M3VVWW5",
      "riskyWindow": {
        "from": "2021-07-03T00:00:00Z",
        "until": "2021-07-03T22:59:00Z"
      },
      "messageType": "M2"
    },
    {
      "id": "5Y83V6MR",
      "riskyWindow": {
        "from": "2021-07-04T00:00:00Z",
        "until": "2021-07-04T22:59:00Z"
      },
      "messageType": "M2"
    },
    {
      "id": "RK6KK825",
      "riskyWindow": {
        "from": "2021-07-03T00:00:00Z",
        "until": "2021-07-03T22:59:00Z"
      },
      "messageType": "M2"
    },
    {
      "id": "53X2X2YR",
      "riskyWindow": {
        "from": "2021-07-03T00:00:00Z",
        "until": "2021-07-03T22:59:00Z"
      },
      "messageType": "M2"
    },
    {
      "id": "5X892W85",
      "riskyWindow": {
        "from": "2021-07-03T00:00:00Z",
        "until": "2021-07-03T22:59:00Z"
      },
      "messageType": "M2"
    },
    {
      "id": "5VXX9V35",
      "riskyWindow": {
        "from": "2021-07-04T00:00:00Z",
        "until": "2021-07-04T22:59:00Z"
      },
      "messageType": "M2"
    },
    {
      "id": "V5V986YR",
      "riskyWindow": {
        "from": "2021-07-03T00:00:00Z",
        "until": "2021-07-03T22:59:00Z"
      },
      "messageType": "M2"
    },
    {
      "id": "5WMMK9X5",
      "riskyWindow": {
        "from": "2021-07-04T00:00:00Z",
        "until": "2021-07-04T22:59:00Z"
      },
      "messageType": "M2"
    },
    {
      "id": "542J3VVY",
      "riskyWindow": {
        "from": "2021-07-03T00:00:00Z",
        "until": "2021-07-03T22:59:00Z"
      },
      "messageType": "M2"
    },
    {
      "id": "5WV2MMJ8",
      "riskyWindow": {
        "from": "2021-07-03T00:00:00Z",
        "until": "2021-07-03T22:59:00Z"
      },
      "messageType": "M2"
    },
    {
      "id": "5M3MWKY5",
      "riskyWindow": {
        "from": "2021-07-03T00:00:00Z",
        "until": "2021-07-03T22:59:00Z"
      },
      "messageType": "M2"
    },
    {
      "id": "5VXM69KK",
      "riskyWindow": {
        "from": "2021-07-05T00:00:00Z",
        "until": "2021-07-05T22:59:00Z"
      },
      "messageType": "M2"
    },
    {
      "id": "X5X96JYR",
      "riskyWindow": {
        "from": "2021-07-04T00:00:00Z",
        "until": "2021-07-04T22:59:00Z"
      },
      "messageType": "M2"
    },
    {
      "id": "5V64XY85",
      "riskyWindow": {
        "from": "2021-07-04T00:00:00Z",
        "until": "2021-07-04T22:59:00Z"
      },
      "messageType": "M2"
    },
    {
      "id": "5WP2X6JR",
      "riskyWindow": {
        "from": "2021-07-05T00:00:00Z",
        "until": "2021-07-05T22:59:00Z"
      },
      "messageType": "M2"
    },
    {
      "id": "4RJ9XX95",
      "riskyWindow": {
        "from": "2021-07-03T00:00:00Z",
        "until": "2021-07-03T22:59:00Z"
      },
      "messageType": "M2"
    },
    {
      "id": "RK8XVX45",
      "riskyWindow": {
        "from": "2021-07-06T00:00:00Z",
        "until": "2021-07-06T22:59:00Z"
      },
      "messageType": "M2"
    },
    {
      "id": "RK3YKY4R",
      "riskyWindow": {
        "from": "2021-07-02T00:00:00Z",
        "until": "2021-07-02T22:59:00Z"
      },
      "messageType": "M2"
    },
    {
      "id": "53M86JV5",
      "riskyWindow": {
        "from": "2021-07-05T00:00:00Z",
        "until": "2021-07-05T22:59:00Z"
      },
      "messageType": "M2"
    },
    {
      "id": "R8YKYJM5",
      "riskyWindow": {
        "from": "2021-07-06T00:00:00Z",
        "until": "2021-07-06T22:59:00Z"
      },
      "messageType": "M2"
    },
    {
      "id": "5W32J3J5",
      "riskyWindow": {
        "from": "2021-07-03T00:00:00Z",
        "until": "2021-07-03T22:59:00Z"
      },
      "messageType": "M2"
    },
    {
      "id": "52692W85",
      "riskyWindow": {
        "from": "2021-07-06T00:00:00Z",
        "until": "2021-07-06T22:59:00Z"
      },
      "messageType": "M2"
    },
    {
      "id": "542388P5",
      "riskyWindow": {
        "from": "2021-07-04T00:00:00Z",
        "until": "2021-07-04T22:59:00Z"
      },
      "messageType": "M2"
    },
    {
      "id": "RKYX642R",
      "riskyWindow": {
        "from": "2021-07-03T00:00:00Z",
        "until": "2021-07-03T22:59:00Z"
      },
      "messageType": "M2"
    },
    {
      "id": "RPVY24JR",
      "riskyWindow": {
        "from": "2021-07-03T00:00:00Z",
        "until": "2021-07-03T22:59:00Z"
      },
      "messageType": "M2"
    },
    {
      "id": "RP8V8WXR",
      "riskyWindow": {
        "from": "2021-07-05T00:00:00Z",
        "until": "2021-07-05T22:59:00Z"
      },
      "messageType": "M2"
    },
    {
      "id": "X5Y4WXWR",
      "riskyWindow": {
        "from": "2021-07-04T00:00:00Z",
        "until": "2021-07-04T22:59:00Z"
      },
      "messageType": "M2"
    },
    {
      "id": "54JXKV35",
      "riskyWindow": {
        "from": "2021-07-04T00:00:00Z",
        "until": "2021-07-04T22:59:00Z"
      },
      "messageType": "M2"
    },
    {
      "id": "5X2KWKK5",
      "riskyWindow": {
        "from": "2021-07-03T00:00:00Z",
        "until": "2021-07-03T22:59:00Z"
      },
      "messageType": "M2"
    },
    {
      "id": "5W8W63PR",
      "riskyWindow": {
        "from": "2021-07-04T00:00:00Z",
        "until": "2021-07-04T22:59:00Z"
      },
      "messageType": "M2"
    },
    {
      "id": "5W334M85",
      "riskyWindow": {
        "from": "2021-07-04T00:00:00Z",
        "until": "2021-07-04T22:59:00Z"
      },
      "messageType": "M2"
    },
    {
      "id": "RKYM6VM4",
      "riskyWindow": {
        "from": "2021-07-05T00:00:00Z",
        "until": "2021-07-05T22:59:00Z"
      },
      "messageType": "M2"
    },
    {
      "id": "R9X9P2X5",
      "riskyWindow": {
        "from": "2021-07-04T00:00:00Z",
        "until": "2021-07-04T22:59:00Z"
      },
      "messageType": "M2"
    },
    {
      "id": "5338VJY5",
      "riskyWindow": {
        "from": "2021-07-05T00:00:00Z",
        "until": "2021-07-05T22:59:00Z"
      },
      "messageType": "M2"
    },
    {
      "id": "53X342YR",
      "riskyWindow": {
        "from": "2021-07-05T00:00:00Z",
        "until": "2021-07-05T22:59:00Z"
      },
      "messageType": "M2"
    },
    {
      "id": "5WJMXKXR",
      "riskyWindow": {
        "from": "2021-07-03T00:00:00Z",
        "until": "2021-07-03T22:59:00Z"
      },
      "messageType": "M2"
    },
    {
      "id": "V5MMYM95",
      "riskyWindow": {
        "from": "2021-07-04T00:00:00Z",
        "until": "2021-07-04T22:59:00Z"
      },
      "messageType": "M2"
    },
    {
      "id": "568WV895",
      "riskyWindow": {
        "from": "2021-07-03T00:00:00Z",
        "until": "2021-07-03T22:59:00Z"
      },
      "messageType": "M2"
    },
    {
      "id": "RK649Y45",
      "riskyWindow": {
        "from": "2021-07-05T00:00:00Z",
        "until": "2021-07-05T22:59:00Z"
      },
      "messageType": "M2"
    },
    {
      "id": "MR8PK48R",
      "riskyWindow": {
        "from": "2021-07-03T00:00:00Z",
        "until": "2021-07-03T22:59:00Z"
      },
      "messageType": "M2"
    },
    {
      "id": "R9J3WJ65",
      "riskyWindow": {
        "from": "2021-07-03T00:00:00Z",
        "until": "2021-07-03T22:59:00Z"
      },
      "messageType": "M2"
    },
    {
      "id": "5MV2PYYR",
      "riskyWindow": {
        "from": "2021-07-03T00:00:00Z",
        "until": "2021-07-03T22:59:00Z"
      },
      "messageType": "M2"
    },
    {
      "id": "RK34KP8R",
      "riskyWindow": {
        "from": "2021-07-05T00:00:00Z",
        "until": "2021-07-05T22:59:00Z"
      },
      "messageType": "M2"
    },
    {
      "id": "5VX38335",
      "riskyWindow": {
        "from": "2021-06-20T23:01:00Z",
        "until": "2021-06-23T22:59:00Z"
      },
      "messageType": "M2"
    },
    {
      "id": "RJVP42KW",
      "riskyWindow": {
        "from": "2021-07-03T00:00:00Z",
        "until": "2021-07-03T22:59:00Z"
      },
      "messageType": "M2"
    },
    {
      "id": "5VXYMKP5",
      "riskyWindow": {
        "from": "2021-07-06T00:00:00Z",
        "until": "2021-07-06T22:59:00Z"
      },
      "messageType": "M2"
    },
    {
      "id": "5M4KKXYR",
      "riskyWindow": {
        "from": "2021-07-04T00:00:00Z",
        "until": "2021-07-04T22:59:00Z"
      },
      "messageType": "M2"
    },
    {
      "id": "RP8M38XR",
      "riskyWindow": {
        "from": "2021-07-03T00:00:00Z",
        "until": "2021-07-03T22:59:00Z"
      },
      "messageType": "M2"
    },
    {
      "id": "5Y3W2495",
      "riskyWindow": {
        "from": "2021-07-04T00:00:00Z",
        "until": "2021-07-04T22:59:00Z"
      },
      "messageType": "M2"
    },
    {
      "id": "RK8PW965",
      "riskyWindow": {
        "from": "2021-07-04T00:00:00Z",
        "until": "2021-07-04T22:59:00Z"
      },
      "messageType": "M2"
    },
    {
      "id": "5XX96235",
      "riskyWindow": {
        "from": "2021-07-03T00:00:00Z",
        "until": "2021-07-03T22:59:00Z"
      },
      "messageType": "M2"
    },
    {
      "id": "5MVK9PXR",
      "riskyWindow": {
        "from": "2021-07-03T00:00:00Z",
        "until": "2021-07-03T22:59:00Z"
      },
      "messageType": "M2"
    },
    {
      "id": "RKJW3MM5",
      "riskyWindow": {
        "from": "2021-07-03T00:00:00Z",
        "until": "2021-07-03T22:59:00Z"
      },
      "messageType": "M2"
    },
    {
      "id": "R9JYV3J9",
      "riskyWindow": {
        "from": "2021-07-03T00:00:00Z",
        "until": "2021-07-03T22:59:00Z"
      },
      "messageType": "M2"
    },
    {
      "id": "R9P639P5",
      "riskyWindow": {
        "from": "2021-07-04T00:00:00Z",
        "until": "2021-07-04T22:59:00Z"
      },
      "messageType": "M2"
    },
    {
      "id": "RJJW9MWR",
      "riskyWindow": {
        "from": "2021-07-04T00:00:00Z",
        "until": "2021-07-04T22:59:00Z"
      },
      "messageType": "M2"
    },
    {
      "id": "528JYP85",
      "riskyWindow": {
        "from": "2021-07-05T00:00:00Z",
        "until": "2021-07-05T22:59:00Z"
      },
      "messageType": "M2"
    },
    {
      "id": "54W48PXR",
      "riskyWindow": {
        "from": "2021-07-03T00:00:00Z",
        "until": "2021-07-03T22:59:00Z"
      },
      "messageType": "M2"
    },
    {
      "id": "544928X5",
      "riskyWindow": {
        "from": "2021-07-05T00:00:00Z",
        "until": "2021-07-05T22:59:00Z"
      },
      "messageType": "M2"
    },
    {
      "id": "5VK8384R",
      "riskyWindow": {
        "from": "2021-07-05T00:00:00Z",
        "until": "2021-07-05T22:59:00Z"
      },
      "messageType": "M2"
    },
    {
      "id": "5WMV4VJ5",
      "riskyWindow": {
        "from": "2021-07-05T00:00:00Z",
        "until": "2021-07-05T22:59:00Z"
      },
      "messageType": "M2"
    },
    {
      "id": "RP9JV6WV",
      "riskyWindow": {
        "from": "2021-07-03T00:00:00Z",
        "until": "2021-07-03T22:59:00Z"
      },
      "messageType": "M2"
    },
    {
      "id": "RJKJ4465",
      "riskyWindow": {
        "from": "2021-07-03T00:00:00Z",
        "until": "2021-07-03T22:59:00Z"
      },
      "messageType": "M2"
    },
    {
      "id": "549VJW4R",
      "riskyWindow": {
        "from": "2021-07-04T00:00:00Z",
        "until": "2021-07-04T22:59:00Z"
      },
      "messageType": "M2"
    },
    {
      "id": "5XW3963R",
      "riskyWindow": {
        "from": "2021-07-03T00:00:00Z",
        "until": "2021-07-03T22:59:00Z"
      },
      "messageType": "M2"
    },
    {
      "id": "5WVXJJMR",
      "riskyWindow": {
        "from": "2021-07-03T00:00:00Z",
        "until": "2021-07-03T22:59:00Z"
      },
      "messageType": "M2"
    },
    {
      "id": "RK83P235",
      "riskyWindow": {
        "from": "2021-07-04T00:00:00Z",
        "until": "2021-07-04T22:59:00Z"
      },
      "messageType": "M2"
    },
    {
      "id": "5XP369J5",
      "riskyWindow": {
        "from": "2021-07-01T23:01:00Z",
        "until": "2021-07-02T22:59:00Z"
      },
      "messageType": "M2"
    },
    {
      "id": "52WW99J4",
      "riskyWindow": {
        "from": "2021-07-03T00:00:00Z",
        "until": "2021-07-03T22:59:00Z"
      },
      "messageType": "M1"
    },
    {
      "id": "RKY94Y68",
      "riskyWindow": {
        "from": "2021-07-05T00:00:00Z",
        "until": "2021-07-05T22:59:00Z"
      },
      "messageType": "M2"
    },
    {
      "id": "5429MWP3",
      "riskyWindow": {
        "from": "2021-07-04T00:00:00Z",
        "until": "2021-07-04T22:59:00Z"
      },
      "messageType": "M2"
    },
    {
      "id": "5XVWVPW5",
      "riskyWindow": {
        "from": "2021-07-04T00:00:00Z",
        "until": "2021-07-04T22:59:00Z"
      },
      "messageType": "M2"
    },
    {
      "id": "53WPJXXW",
      "riskyWindow": {
        "from": "2021-07-03T00:00:00Z",
        "until": "2021-07-03T22:59:00Z"
      },
      "messageType": "M1"
    },
    {
      "id": "KR96VVP5",
      "riskyWindow": {
        "from": "2021-07-04T00:00:00Z",
        "until": "2021-07-04T22:59:00Z"
      },
      "messageType": "M2"
    },
    {
      "id": "R8K44WK5",
      "riskyWindow": {
        "from": "2021-07-05T00:00:00Z",
        "until": "2021-07-05T22:59:00Z"
      },
      "messageType": "M2"
    },
    {
      "id": "5XYY368R",
      "riskyWindow": {
        "from": "2021-07-03T00:00:00Z",
        "until": "2021-07-03T22:59:00Z"
      },
      "messageType": "M2"
    },
    {
      "id": "568XJ3J3",
      "riskyWindow": {
        "from": "2021-07-03T00:00:00Z",
        "until": "2021-07-03T22:59:00Z"
      },
      "messageType": "M2"
    },
    {
      "id": "R9892W95",
      "riskyWindow": {
        "from": "2021-07-03T00:00:00Z",
        "until": "2021-07-03T22:59:00Z"
      },
      "messageType": "M2"
    },
    {
      "id": "5V8Y3PP5",
      "riskyWindow": {
        "from": "2021-07-03T00:00:00Z",
        "until": "2021-07-03T22:59:00Z"
      },
      "messageType": "M1"
    },
    {
      "id": "5VX28J44",
      "riskyWindow": {
        "from": "2021-07-03T00:00:00Z",
        "until": "2021-07-03T22:59:00Z"
      },
      "messageType": "M2"
    },
    {
      "id": "533WJ625",
      "riskyWindow": {
        "from": "2021-07-04T00:00:00Z",
        "until": "2021-07-04T22:59:00Z"
      },
      "messageType": "M2"
    },
    {
      "id": "RKYWPYVK",
      "riskyWindow": {
        "from": "2021-07-05T00:00:00Z",
        "until": "2021-07-05T22:59:00Z"
      },
      "messageType": "M2"
    },
    {
      "id": "RP2V4VJR",
      "riskyWindow": {
        "from": "2021-07-03T00:00:00Z",
        "until": "2021-07-03T22:59:00Z"
      },
      "messageType": "M1"
    },
    {
      "id": "5MP8P8VR",
      "riskyWindow": {
        "from": "2021-07-03T00:00:00Z",
        "until": "2021-07-03T22:59:00Z"
      },
      "messageType": "M1"
    },
    {
      "id": "5WKXVKW5",
      "riskyWindow": {
        "from": "2021-07-03T00:00:00Z",
        "until": "2021-07-03T22:59:00Z"
      },
      "messageType": "M2"
    },
    {
      "id": "R84P4VKR",
      "riskyWindow": {
        "from": "2021-07-03T00:00:00Z",
        "until": "2021-07-03T22:59:00Z"
      },
      "messageType": "M2"
    },
    {
      "id": "R9P96XV5",
      "riskyWindow": {
        "from": "2021-07-03T00:00:00Z",
        "until": "2021-07-03T22:59:00Z"
      },
      "messageType": "M2"
    },
    {
      "id": "KRP933V5",
      "riskyWindow": {
        "from": "2021-07-03T00:00:00Z",
        "until": "2021-07-03T22:59:00Z"
      },
      "messageType": "M1"
    },
    {
      "id": "544YW645",
      "riskyWindow": {
        "from": "2021-07-03T00:00:00Z",
        "until": "2021-07-03T22:59:00Z"
      },
      "messageType": "M1"
    },
    {
      "id": "5Y93V995",
      "riskyWindow": {
        "from": "2021-07-03T00:00:00Z",
        "until": "2021-07-03T22:59:00Z"
      },
      "messageType": "M2"
    },
    {
      "id": "R9J6J3PX",
      "riskyWindow": {
        "from": "2021-07-03T00:00:00Z",
        "until": "2021-07-03T22:59:00Z"
      },
      "messageType": "M2"
    },
    {
      "id": "53W4W49Y",
      "riskyWindow": {
        "from": "2021-07-03T00:00:00Z",
        "until": "2021-07-03T22:59:00Z"
      },
      "messageType": "M1"
    },
    {
      "id": "5Y923M95",
      "riskyWindow": {
        "from": "2021-07-03T00:00:00Z",
        "until": "2021-07-03T22:59:00Z"
      },
      "messageType": "M2"
    },
    {
      "id": "R8V3386M",
      "riskyWindow": {
        "from": "2021-07-03T00:00:00Z",
        "until": "2021-07-03T22:59:00Z"
      },
      "messageType": "M2"
    },
    {
      "id": "5YK6Y4M5",
      "riskyWindow": {
        "from": "2021-07-03T00:00:00Z",
        "until": "2021-07-03T22:59:00Z"
      },
      "messageType": "M2"
    },
    {
      "id": "M5392845",
      "riskyWindow": {
        "from": "2021-07-03T00:00:00Z",
        "until": "2021-07-03T22:59:00Z"
      },
      "messageType": "M2"
    },
    {
      "id": "5WYK9YJ5",
      "riskyWindow": {
        "from": "2021-07-04T00:00:00Z",
        "until": "2021-07-04T22:59:00Z"
      },
      "messageType": "M2"
    },
    {
      "id": "V54M3MYR",
      "riskyWindow": {
        "from": "2021-07-03T00:00:00Z",
        "until": "2021-07-03T22:59:00Z"
      },
      "messageType": "M2"
    },
    {
      "id": "5VPJ4KK5",
      "riskyWindow": {
        "from": "2021-07-04T00:00:00Z",
        "until": "2021-07-04T22:59:00Z"
      },
      "messageType": "M2"
    },
    {
      "id": "RKYXY2P3",
      "riskyWindow": {
        "from": "2021-07-04T00:00:00Z",
        "until": "2021-07-04T22:59:00Z"
      },
      "messageType": "M2"
    },
    {
      "id": "53X9PY2R",
      "riskyWindow": {
        "from": "2021-07-03T00:00:00Z",
        "until": "2021-07-03T22:59:00Z"
      },
      "messageType": "M2"
    },
    {
      "id": "5X4JPPW5",
      "riskyWindow": {
        "from": "2021-07-03T00:00:00Z",
        "until": "2021-07-03T22:59:00Z"
      },
      "messageType": "M2"
    },
    {
      "id": "KR9XPJ25",
      "riskyWindow": {
        "from": "2021-07-03T00:00:00Z",
        "until": "2021-07-03T22:59:00Z"
      },
      "messageType": "M2"
    },
    {
      "id": "V5M9JK95",
      "riskyWindow": {
        "from": "2021-07-03T00:00:00Z",
        "until": "2021-07-03T22:59:00Z"
      },
      "messageType": "M1"
    },
    {
      "id": "5WVPP4MR",
      "riskyWindow": {
        "from": "2021-07-03T00:00:00Z",
        "until": "2021-07-03T22:59:00Z"
      },
      "messageType": "M2"
    },
    {
      "id": "5M4PP8XR",
      "riskyWindow": {
        "from": "2021-07-03T00:00:00Z",
        "until": "2021-07-03T22:59:00Z"
      },
      "messageType": "M1"
    },
    {
      "id": "R9JK93WX",
      "riskyWindow": {
        "from": "2021-07-04T00:00:00Z",
        "until": "2021-07-04T22:59:00Z"
      },
      "messageType": "M1"
    },
    {
      "id": "4RJ9V3W5",
      "riskyWindow": {
        "from": "2021-07-03T00:00:00Z",
        "until": "2021-07-03T22:59:00Z"
      },
      "messageType": "M2"
    },
    {
      "id": "53W8K68Y",
      "riskyWindow": {
        "from": "2021-07-05T00:00:00Z",
        "until": "2021-07-05T22:59:00Z"
      },
      "messageType": "M2"
    },
    {
      "id": "R8PMV49R",
      "riskyWindow": {
        "from": "2021-07-03T00:00:00Z",
        "until": "2021-07-03T22:59:00Z"
      },
      "messageType": "M1"
    },
    {
      "id": "RJVYPJ6R",
      "riskyWindow": {
        "from": "2021-07-03T00:00:00Z",
        "until": "2021-07-03T22:59:00Z"
      },
      "messageType": "M2"
    },
    {
      "id": "RP9P4K42",
      "riskyWindow": {
        "from": "2021-07-03T00:00:00Z",
        "until": "2021-07-03T22:59:00Z"
      },
      "messageType": "M2"
    },
    {
      "id": "P524MKK5",
      "riskyWindow": {
        "from": "2021-07-04T00:00:00Z",
        "until": "2021-07-04T22:59:00Z"
      },
      "messageType": "M2"
    },
    {
      "id": "5WV4MJJR",
      "riskyWindow": {
        "from": "2021-07-03T00:00:00Z",
        "until": "2021-07-03T22:59:00Z"
      },
      "messageType": "M2"
    },
    {
      "id": "5M82KKVR",
      "riskyWindow": {
        "from": "2021-07-03T00:00:00Z",
        "until": "2021-07-03T22:59:00Z"
      },
      "messageType": "M1"
    },
    {
      "id": "R9JWK6V5",
      "riskyWindow": {
        "from": "2021-07-03T00:00:00Z",
        "until": "2021-07-03T22:59:00Z"
      },
      "messageType": "M2"
    },
    {
      "id": "5X2M32Y5",
      "riskyWindow": {
        "from": "2021-07-03T00:00:00Z",
        "until": "2021-07-03T22:59:00Z"
      },
      "messageType": "M2"
    },
    {
      "id": "4RJY3PM5",
      "riskyWindow": {
        "from": "2021-07-04T00:00:00Z",
        "until": "2021-07-04T22:59:00Z"
      },
      "messageType": "M2"
    },
    {
      "id": "5VX2MPY9",
      "riskyWindow": {
        "from": "2021-07-04T00:00:00Z",
        "until": "2021-07-04T22:59:00Z"
      },
      "messageType": "M2"
    },
    {
      "id": "5WVMYMYM",
      "riskyWindow": {
        "from": "2021-07-04T00:00:00Z",
        "until": "2021-07-04T22:59:00Z"
      },
      "messageType": "M1"
    },
    {
      "id": "548MY645",
      "riskyWindow": {
        "from": "2021-07-04T00:00:00Z",
        "until": "2021-07-04T22:59:00Z"
      },
      "messageType": "M2"
    },
    {
      "id": "R84JPX8R",
      "riskyWindow": {
        "from": "2021-07-04T00:00:00Z",
        "until": "2021-07-04T22:59:00Z"
      },
      "messageType": "M2"
    },
    {
      "id": "5W8YKXVR",
      "riskyWindow": {
        "from": "2021-07-03T00:00:00Z",
        "until": "2021-07-03T22:59:00Z"
      },
      "messageType": "M1"
    },
    {
      "id": "4RJ83VVR",
      "riskyWindow": {
        "from": "2021-07-03T00:00:00Z",
        "until": "2021-07-03T22:59:00Z"
      },
      "messageType": "M2"
    },
    {
      "id": "RPVKK99R",
      "riskyWindow": {
        "from": "2021-07-03T00:00:00Z",
        "until": "2021-07-03T22:59:00Z"
      },
      "messageType": "M2"
    },
    {
      "id": "52KWPPPR",
      "riskyWindow": {
        "from": "2021-07-04T00:00:00Z",
        "until": "2021-07-04T22:59:00Z"
      },
      "messageType": "M2"
    },
    {
      "id": "RJK6K9V5",
      "riskyWindow": {
        "from": "2021-07-04T00:00:00Z",
        "until": "2021-07-04T22:59:00Z"
      },
      "messageType": "M2"
    },
    {
      "id": "53VKPXJR",
      "riskyWindow": {
        "from": "2021-07-03T00:00:00Z",
        "until": "2021-07-03T22:59:00Z"
      },
      "messageType": "M2"
    },
    {
      "id": "RJMJ6V25",
      "riskyWindow": {
        "from": "2021-07-05T00:00:00Z",
        "until": "2021-07-05T22:59:00Z"
      },
      "messageType": "M2"
    },
    {
      "id": "RJVXM88R",
      "riskyWindow": {
        "from": "2021-07-04T00:00:00Z",
        "until": "2021-07-04T22:59:00Z"
      },
      "messageType": "M1"
    },
    {
      "id": "52V43P95",
      "riskyWindow": {
        "from": "2021-07-03T00:00:00Z",
        "until": "2021-07-03T22:59:00Z"
      },
      "messageType": "M2"
    },
    {
      "id": "568WPJV4",
      "riskyWindow": {
        "from": "2021-07-04T00:00:00Z",
        "until": "2021-07-04T22:59:00Z"
      },
      "messageType": "M2"
    },
    {
      "id": "R9J6PW65",
      "riskyWindow": {
        "from": "2021-07-03T00:00:00Z",
        "until": "2021-07-03T22:59:00Z"
      },
      "messageType": "M2"
    },
    {
      "id": "5YPWXYPR",
      "riskyWindow": {
        "from": "2021-07-04T00:00:00Z",
        "until": "2021-07-04T22:59:00Z"
      },
      "messageType": "M2"
    },
    {
      "id": "532YKVJR",
      "riskyWindow": {
        "from": "2021-07-03T00:00:00Z",
        "until": "2021-07-03T22:59:00Z"
      },
      "messageType": "M2"
    },
    {
      "id": "RK8W2JK5",
      "riskyWindow": {
        "from": "2021-07-03T00:00:00Z",
        "until": "2021-07-03T22:59:00Z"
      },
      "messageType": "M2"
    },
    {
      "id": "538YJXYR",
      "riskyWindow": {
        "from": "2021-07-03T00:00:00Z",
        "until": "2021-07-03T22:59:00Z"
      },
      "messageType": "M2"
    },
    {
      "id": "5WV36XXV",
      "riskyWindow": {
        "from": "2021-07-04T00:00:00Z",
        "until": "2021-07-04T22:59:00Z"
      },
      "messageType": "M1"
    },
    {
      "id": "5WXVPWWR",
      "riskyWindow": {
        "from": "2021-07-04T00:00:00Z",
        "until": "2021-07-04T22:59:00Z"
      },
      "messageType": "M2"
    },
    {
      "id": "X5X43WW5",
      "riskyWindow": {
        "from": "2021-07-03T00:00:00Z",
        "until": "2021-07-03T22:59:00Z"
      },
      "messageType": "M1"
    },
    {
      "id": "53WJX9XJ",
      "riskyWindow": {
        "from": "2021-07-03T00:00:00Z",
        "until": "2021-07-03T22:59:00Z"
      },
      "messageType": "M1"
    },
    {
      "id": "56896PJ5",
      "riskyWindow": {
        "from": "2021-07-03T00:00:00Z",
        "until": "2021-07-03T22:59:00Z"
      },
      "messageType": "M1"
    },
    {
      "id": "RK9K638R",
      "riskyWindow": {
        "from": "2021-07-04T00:00:00Z",
        "until": "2021-07-04T22:59:00Z"
      },
      "messageType": "M2"
    },
    {
      "id": "5YY96YY5",
      "riskyWindow": {
        "from": "2021-07-04T00:00:00Z",
        "until": "2021-07-04T22:59:00Z"
      },
      "messageType": "M2"
    },
    {
      "id": "5XVVW685",
      "riskyWindow": {
        "from": "2021-07-03T00:00:00Z",
        "until": "2021-07-03T22:59:00Z"
      },
      "messageType": "M2"
    },
    {
      "id": "RKYMP2V8",
      "riskyWindow": {
        "from": "2021-07-03T00:00:00Z",
        "until": "2021-07-03T22:59:00Z"
      },
      "messageType": "M2"
    }
  ]
}
